Workbook

Sheet Sales Performance Analysis
A1: Summary Average of Order
A2: Year | B2: Revenue | C2: Total Transaction | D2: AOV(Average Order)
A3: 2020 | B3: =GETPIVOTDATA("TotalOrderTransaction",$A$10,"Years (OrderDate)",2020) -> 111070848160 | C3: =COUNTIFS('Sales Order'!D$1:D$1029,">=01/01/2020",'Sales Order'!D$1:D$1029,"<=31/12/2020") -> 355 | D3: =B3/C3 -> 3.1287563e+08
A4: 2021 | B4: =GETPIVOTDATA("TotalOrderTransaction",$A$10,"Years (OrderDate)",2021) -> 91960394232 | C4: =COUNTIFS('Sales Order'!D$1:D$1029,">=01/01/2021",'Sales Order'!D$1:D$1029,"<=31/12/2021") -> 326 | D4: =B4/C4 -> 2.820871e+08
A5: 2022 | B5: =GETPIVOTDATA("TotalOrderTransaction",$A$10,"Years (OrderDate)",2022) -> 93738658411 | C5: =COUNTIFS('Sales Order'!D$1:D$1029,">=01/01/2022",'Sales Order'!D$1:D$1029,"<=31/12/2022") -> 347 | D5: =B5/C5 -> 2.7014023e+08
A6: Total 2020 - 2022 | B6: =SUM(B3:B5) -> 296769900803 | C6: =SUM(C3:C5) -> 1028 | D6: =B6/C6 -> 2.8868667e+08
A9: Sales Trend
A10: Row Labels | B10: Sum of TotalOrderTransaction
A11: 2020 | B11: 111070848160
A12: Jan | B12: 8413435101
A13: Feb | B13: 8873118039
A14: Mar | B14: 9403906569
A15: Apr | B15: 13014811284
A16: May | B16: 7369746605
A17: Jun | B17: 9495793700
A18: Jul | B18: 6938459794
A19: Aug | B19: 9982499020
A20: Sep | B20: 5559243162
A21: Oct | B21: 6688805798
A22: Nov | B22: 13241776433
... A50: Grand Total | B50: 296769900803
A51: Seasonality
A52: Sum of TotalOrderTransaction | B52: Column Labels
A53: Row Labels | B53: 2020 | C53: 2021 | D53: 2022 | E53: Grand Total
A54: Jan | B54: 8413435101 | C54: 6006920922 | D54: 8994015941 | E54: 23414371964
A55: Feb | B55: 8873118039 | C55: 10810944665 | D55: 6143660865 | E55: 25827723569
A56: Mar | B56: 9403906569 | C56: 10531075262 | D56: 7050162013 | E56: 26985143844
A57: Apr | B57: 13014811284 | C57: 5909070377 | D57: 10076428067 | E57: 29000309728
A58: May | B58: 7369746605 | C58: 10961188957 | D58: 8990850316 | E58: 27321785878
A59: Jun | B59: 9495793700 | C59: 7378988884 | D59: 6694582334 | E59: 23569364918
A60: Jul | B60: 6938459794 | C60: 6490006504 | D60: 4903260764 | E60: 18331727062
A61: Aug | B61: 9982499020 | C61: 7748171035 | D61: 6487507383 | E61: 24218177438
A62: Sep | B62: 5559243162 | C62: 3724306588 | D62: 8517428394 | E62: 17800978144
A63: Oct | B63: 6688805798 | C63: 7350906379 | D63: 13173162638 | E63: 27212874815
A64: Nov | B64: 13241776433 | C64: 7823993577 | D64: 7891588474 | E64: 28957358484
A65: Dec | B65: 12089252655 | C65: 7224821082 | D65: 4816011222 | E65: 24130084959
A66: Grand Total | B66: 111070848160 | C66: 91960394232 | D66: 93738658411 | E66: 296769900803
A88: Growth Analysis(comparing sales MoM & YoY)
A89: MoM | B89: 1st month to compare data | C89: 2nd month to compare data | D89: Growth Percentage
A90: Jan 2020 - Feb 2020 | B90: 8413435101 | C90: 8873118039 | D90: =(C90-B90)/B90 -> 0.054636772
A91: Feb 2020 - Mar 2020 | B91: 8873118039 | C91: 9403906569 | D91: =(C91-B91)/B91 -> 0.059819843
A92: Mar 2020 - Apr 2020 | B92: 9403906569 | C92: 13014811284 | D92: =(C92-B92)/B92 -> 0.38397922
A93: Apr 2020 - May 2020 | B93: 13014811284 | C93: 7369746605 | D93: =(C93-B93)/B93 -> -0.43374157
A94: May 2020 - Jun 2020 | B94: 7369746605 | C94: 9495793700 | D94: =(C94-B94)/B94 -> 0.28848307
A95: Jun 2020 - Jul 2020 | B95: 9495793700 | C95: 6938459794 | D95: =(C95-B95)/B95 -> -0.26931229
A96: Jul 2020 - Aug 2020 | B96: 6938459794 | C96: 9982499020 | D96: =(C96-B96)/B96 -> 0.43871973
A97: Aug 2020 - Sep 2020 | B97: 9982499020 | C97: 5559243162 | D97: =(C97-B97)/B97 -> -0.44310106
A98: Sep 2020 - Okt 2020 | B98: 5559243162 | C98: 6688805798 | D98: =(C98-B98)/B98 -> 0.20318641
A99: Okt 2020 - Nov 2020 | B99: 6688805798 | C99: 13241776433 | D99: =(C99-B99)/B99 -> 0.97969217
A100: Nov 2020 - Des 2020 | B100: 13241776433 | C100: 12089252655 | D100: =(C100-B100)/B100 -> -0.087036946
A101: Des 2020 - Jan 2021 | B101: 12089252655 | C101: 6006920922 | D101: =(C101-B101)/B101 -> -0.50311892
... A124: Nov 2022 - Des 2022 | B124: 7891588474 | C124: 4816011222 | D124: =(C124-B124)/B124 -> -0.38972854
A126: YoY | B126: 1st year to compare data | C126: 2nd year to compare data | D126: Growth Percentage
A127: 2020 - 2021 | B127: 111070848160 | C127: 91960394232 | D127: =(C127-B127)/B127 -> -0.17205643
A128: 2021 - 2022 | B128: 91960394232 | C128: 93738658411 | D128: =(C128-B128)/B128 -> 0.019337283
A135: Sales Distribution
A136: Histogram | D136: Boxplot

Sheet Sales Order
A1: SalesOrderID | B1: PatnerStoreID | C1: SalesTeamID | D1: OrderDate | E1: Region Sales | F1: Payment | G1: TotalOrderTransaction | H1: Note | I1: Region Sales Team | J1: Sales Teams Method | K1: Patner Store | L1: Patner Type | M1: Region_Sales | N1: Province_Sales
A2: SO0001 | B2: PS0040 | C2: ST0003 | D2: 43832 | E2: Sumatera & Kalimantan | F2: CASH | G2: 114641676 | I2: =VLOOKUP(C2,'Sales Team'!A$1:C$6,2,0) -> Sales Sumatera -Kalimantan Region Team | J2: =VLOOKUP(C2,'Sales Team'!A$1:D$6,4,0) -> OnlineMarketing/Corporate Negotiate/Patnership Contract | K2: =VLOOKUP(B2,'Patner Store'!A$1:F$51,2,0) -> Olahraga Gemilang | L2: =VLOOKUP(B2,'Patner Store'!A$1:F$51,3,0) -> Retail | M2: =VLOOKUP(B2,'Patner Store'!A$1:F$51,4,0) -> Kalimantan | N2: =VLOOKUP(B2,'Patner Store'!A$1:F$51,5,0) -> Central Kalimantan
A3: SO0002 | B3: PS0046 | C3: ST0003 | D3: 43832 | E3: Sumatera & Kalimantan | F3: CASH | G3: 44870970 | I3: =VLOOKUP(C3,'Sales Team'!A$1:C$6,2,0) -> Sales Sumatera -Kalimantan Region Team | J3: =VLOOKUP(C3,'Sales Team'!A$1:D$6,4,0) -> OnlineMarketing/Corporate Negotiate/Patnership Contract | K3: =VLOOKUP(B3,'Patner Store'!A$1:F$51,2,0) -> Markas Olahraga | L3: =VLOOKUP(B3,'Patner Store'!A$1:F$51,3,0) -> Retail | M3: =VLOOKUP(B3,'Patner Store'!A$1:F$51,4,0) -> Kalimantan | N3: =VLOOKUP(B3,'Patner Store'!A$1:F$51,5,0) -> South Kalimantan
A4: SO0003 | B4: PS0024 | C4: ST0001 | D4: 43833 | E4: Jakarta | F4: CREDIT | G4: 1101806050 | H4: transaction as agreed with the vendor | I4: =VLOOKUP(C4,'Sales Team'!A$1:C$6,2,0) -> Online Sales Team | J4: =VLOOKUP(C4,'Sales Team'!A$1:D$6,4,0) -> OnlineMarketing | K4: =VLOOKUP(B4,'Patner Store'!A$1:F$51,2,0) -> SportChampion10 | L4: =VLOOKUP(B4,'Patner Store'!A$1:F$51,3,0) -> Retail | M4: =VLOOKUP(B4,'Patner Store'!A$1:F$51,4,0) -> Java | N4: =VLOOKUP(B4,'Patner Store'!A$1:F$51,5,0) -> Jakarta
A5: SO0004 | B5: PS0048 | C5: ST0003 | D5: 43834 | E5: Sumatera & Kalimantan | F5: CASH | G5: 10698048 | I5: =VLOOKUP(C5,'Sales Team'!A$1:C$6,2,0) -> Sales Sumatera -Kalimantan Region Team | J5: =VLOOKUP(C5,'Sales Team'!A$1:D$6,4,0) -> OnlineMarketing/Corporate Negotiate/Patnership Contract | K5: =VLOOKUP(B5,'Patner Store'!A$1:F$51,2,0) -> Toko Olahraga Mandiri | L5: =VLOOKUP(B5,'Patner Store'!A$1:F$51,3,0) -> Retail | M5: =VLOOKUP(B5,'Patner Store'!A$1:F$51,4,0) -> Kalimantan | N5: =VLOOKUP(B5,'Patner Store'!A$1:F$51,5,0) -> South Kalimantan
A6: SO0005 | B6: PS0024 | C6: ST0001 | D6: 43835 | E6: Jakarta | F6: CREDIT | G6: 250560000 | I6: =VLOOKUP(C6,'Sales Team'!A$1:C$6,2,0) -> Online Sales Team | J6: =VLOOKUP(C6,'Sales Team'!A$1:D$6,4,0) -> OnlineMarketing | K6: =VLOOKUP(B6,'Patner Store'!A$1:F$51,2,0) -> SportChampion10 | L6: =VLOOKUP(B6,'Patner Store'!A$1:F$51,3,0) -> Retail | M6: =VLOOKUP(B6,'Patner Store'!A$1:F$51,4,0) -> Java | N6: =VLOOKUP(B6,'Patner Store'!A$1:F$51,5,0) -> Jakarta
A7: SO0006 | B7: PS0012 | C7: ST0003 | D7: 43837 | E7: Sumatera & Kalimantan | F7: CASH | G7: 11269440 | I7: =VLOOKUP(C7,'Sales Team'!A$1:C$6,2,0) -> Sales Sumatera -Kalimantan Region Team | J7: =VLOOKUP(C7,'Sales Team'!A$1:D$6,4,0) -> OnlineMarketing/Corporate Negotiate/Patnership Contract | K7: =VLOOKUP(B7,'Patner Store'!A$1:F$51,2,0) -> Adi Shop | L7: =VLOOKUP(B7,'Patner Store'!A$1:F$51,3,0) -> Retail | M7: =VLOOKUP(B7,'Patner Store'!A$1:F$51,4,0) -> Kalimantan | N7: =VLOOKUP(B7,'Patner Store'!A$1:F$51,5,0) -> South Kalimantan
A8: SO0007 | B8: PS0024 | C8: ST0001 | D8: 43839 | E8: Jakarta | F8: CREDIT | G8: 427027780 | I8: =VLOOKUP(C8,'Sales Team'!A$1:C$6,2,0) -> Online Sales Team | J8: =VLOOKUP(C8,'Sales Team'!A$1:D$6,4,0) -> OnlineMarketing | K8: =VLOOKUP(B8,'Patner Store'!A$1:F$51,2,0) -> SportChampion10 | L8: =VLOOKUP(B8,'Patner Store'!A$1:F$51,3,0) -> Retail | M8: =VLOOKUP(B8,'Patner Store'!A$1:F$51,4,0) -> Java | N8: =VLOOKUP(B8,'Patner Store'!A$1:F$51,5,0) -> Jakarta
A9: SO0008 | B9: PS0045 | C9: ST0005 | D9: 43840 | E9: Bali, East & West Nusa Tenggara | F9: CREDIT | G9: 614116940 | I9: =VLOOKUP(C9,'Sales Team'!A$1:C$6,2,0) -> Sales Region Bali - Nusa Tenggara Team | J9: =VLOOKUP(C9,'Sales Team'!A$1:D$6,4,0) -> Corporate Negotiate/Patnership Contract | K9: =VLOOKUP(B9,'Patner Store'!A$1:F$51,2,0) -> Toko Olahraga NTB | L9: =VLOOKUP(B9,'Patner Store'!A$1:F$51,3,0) -> Retail | M9: =VLOOKUP(B9,'Patner Store'!A$1:F$51,4,0) -> Nusa Tenggara | N9: =VLOOKUP(B9,'Patner Store'!A$1:F$51,5,0) -> West Nusa Tenggara
A10: SO0009 | B10: PS0037 | C10: ST0002 | D10: 43841 | E10: Java | F10: CASH | G10: 175419850 | I10: =VLOOKUP(C10,'Sales Team'!A$1:C$6,2,0) -> Sales Java Region Team | J10: =VLOOKUP(C10,'Sales Team'!A$1:D$6,4,0) -> OnlineMarketing/Corporate Negotiate/Patnership Contract | K10: =VLOOKUP(B10,'Patner Store'!A$1:F$51,2,0) -> Toko Joko Sport | L10: =VLOOKUP(B10,'Patner Store'!A$1:F$51,3,0) -> Retail | M10: =VLOOKUP(B10,'Patner Store'!A$1:F$51,4,0) -> Java | N10: =VLOOKUP(B10,'Patner Store'!A$1:F$51,5,0) -> East Java
A11: SO0010 | B11: PS0037 | C11: ST0002 | D11: 43841 | E11: Java | F11: CREDIT | G11: 669084987 | I11: =VLOOKUP(C11,'Sales Team'!A$1:C$6,2,0) -> Sales Java Region Team | J11: =VLOOKUP(C11,'Sales Team'!A$1:D$6,4,0) -> OnlineMarketing/Corporate Negotiate/Patnership Contract | K11: =VLOOKUP(B11,'Patner Store'!A$1:F$51,2,0) -> Toko Joko Sport | L11: =VLOOKUP(B11,'Patner Store'!A$1:F$51,3,0) -> Retail | M11: =VLOOKUP(B11,'Patner Store'!A$1:F$51,4,0) -> Java | N11: =VLOOKUP(B11,'Patner Store'!A$1:F$51,5,0) -> East Java
A12: SO0011 | B12: PS0003 | C12: ST0003 | D12: 43843 | E12: Sumatera & Kalimantan | F12: CASH | G12: 70191310 | H12: The transaction agreement has undergone changes | I12: =VLOOKUP(C12,'Sales Team'!A$1:C$6,2,0) -> Sales Sumatera -Kalimantan Region Team | J12: =VLOOKUP(C12,'Sales Team'!A$1:D$6,4,0) -> OnlineMarketing/Corporate Negotiate/Patnership Contract | K12: =VLOOKUP(B12,'Patner Store'!A$1:F$51,2,0) -> Toko Gelora Sport | L12: =VLOOKUP(B12,'Patner Store'!A$1:F$51,3,0) -> Retail | M12: =VLOOKUP(B12,'Patner Store'!A$1:F$51,4,0) -> Kalimantan | N12: =VLOOKUP(B12,'Patner Store'!A$1:F$51,5,0) -> Central Kalimantan
A13: SO0012 | B13: PS0043 | C13: ST0004 | D13: 43847 | E13: Sulawesi, Maluku, North Maluku | F13: CASH | G13: 97549900 | I13: =VLOOKUP(C13,'Sales Team'!A$1:C$6,2,0) -> Sales Region Sulawesi - Maluku Team | J13: =VLOOKUP(C13,'Sales Team'!A$1:D$6,4,0) -> Corporate Negotiate/Patnership Contract | K13: =VLOOKUP(B13,'Patner Store'!A$1:F$51,2,0) -> SportMania Store | L13: =VLOOKUP(B13,'Patner Store'!A$1:F$51,3,0) -> Retail | M13: =VLOOKUP(B13,'Patner Store'!A$1:F$51,4,0) -> North Maluku | N13: =VLOOKUP(B13,'Patner Store'!A$1:F$51,5,0) -> North Maluku
A14: SO0013 | B14: PS0050 | C14: ST0004 | D14: 43848 | E14: Sulawesi, Maluku, North Maluku | F14: CREDIT | G14: 637102960 | I14: =VLOOKUP(C14,'Sales Team'!A$1:C$6,2,0) -> Sales Region Sulawesi - Maluku Team | J14: =VLOOKUP(C14,'Sales Team'!A$1:D$6,4,0) -> Corporate Negotiate/Patnership Contract | K14: =VLOOKUP(B14,'Patner Store'!A$1:F$51,2,0) -> Toko Peralatan Olahraga | L14: =VLOOKUP(B14,'Patner Store'!A$1:F$51,3,0) -> Retail | M14: =VLOOKUP(B14,'Patner Store'!A$1:F$51,4,0) -> Maluku | N14: =VLOOKUP(B14,'Patner Store'!A$1:F$51,5,0) -> Maluku
A15: SO0014 | B15: PS0032 | C15: ST0004 | D15: 43849 | E15: Sulawesi, Maluku, North Maluku | F15: CREDIT | G15: 290103980 | I15: =VLOOKUP(C15,'Sales Team'!A$1:C$6,2,0) -> Sales Region Sulawesi - Maluku Team | J15: =VLOOKUP(C15,'Sales Team'!A$1:D$6,4,0) -> Corporate Negotiate/Patnership Contract | K15: =VLOOKUP(B15,'Patner Store'!A$1:F$51,2,0) -> Toko Idola Olahraga | L15: =VLOOKUP(B15,'Patner Store'!A$1:F$51,3,0) -> Retail | M15: =VLOOKUP(B15,'Patner Store'!A$1:F$51,4,0) -> Sulawesi | N15: =VLOOKUP(B15,'Patner Store'!A$1:F$51,5,0) -> North Sulawesi
A16: SO0015 | B16: PS0014 | C16: ST0003 | D16: 43850 | E16: Sumatera & Kalimantan | F16: CREDIT | G16: 644706190 | H16: transaction as agreed with the vendor | I16: =VLOOKUP(C16,'Sales Team'!A$1:C$6,2,0) -> Sales Sumatera -Kalimantan Region Team | J16: =VLOOKUP(C16,'Sales Team'!A$1:D$6,4,0) -> OnlineMarketing/Corporate Negotiate/Patnership Contract | K16: =VLOOKUP(B16,'Patner Store'!A$1:F$51,2,0) -> Sport Hub Medan | L16: =VLOOKUP(B16,'Patner Store'!A$1:F$51,3,0) -> Distributor | M16: =VLOOKUP(B16,'Patner Store'!A$1:F$51,4,0) -> Sumatera | N16: =VLOOKUP(B16,'Patner Store'!A$1:F$51,5,0) -> North Sumatera
A17: SO0016 | B17: PS0008 | C17: ST0004 | D17: 43850 | E17: Sulawesi, Maluku, North Maluku | F17: CASH | G17: 248020740 | H17: Partner Store canceled the order | I17: =VLOOKUP(C17,'Sales Team'!A$1:C$6,2,0) -> Sales Region Sulawesi - Maluku Team | J17: =VLOOKUP(C17,'Sales Team'!A$1:D$6,4,0) -> Corporate Negotiate/Patnership Contract | K17: =VLOOKUP(B17,'Patner Store'!A$1:F$51,2,0) -> Amanah Sport | L17: =VLOOKUP(B17,'Patner Store'!A$1:F$51,3,0) -> Retail | M17: =VLOOKUP(B17,'Patner Store'!A$1:F$51,4,0) -> Sulawesi | N17: =VLOOKUP(B17,'Patner Store'!A$1:F$51,5,0) -> North Sulawesi
A18: SO0017 | B18: PS0013 | C18: ST0001 | D18: 43853 | E18: Jakarta | F18: CREDIT | G18: 688063360 | I18: =VLOOKUP(C18,'Sales Team'!A$1:C$6,2,0) -> Online Sales Team | J18: =VLOOKUP(C18,'Sales Team'!A$1:D$6,4,0) -> OnlineMarketing | K18: =VLOOKUP(B18,'Patner Store'!A$1:F$51,2,0) -> Playing Outdoor | L18: =VLOOKUP(B18,'Patner Store'!A$1:F$51,3,0) -> Retail | M18: =VLOOKUP(B18,'Patner Store'!A$1:F$51,4,0) -> Java | N18: =VLOOKUP(B18,'Patner Store'!A$1:F$51,5,0) -> Jakarta
A19: SO0018 | B19: PS0039 | C19: ST0003 | D19: 43853 | E19: Sumatera & Kalimantan | F19: CASH | G19: 44061600 | I19: =VLOOKUP(C19,'Sales Team'!A$1:C$6,2,0) -> Sales Sumatera -Kalimantan Region Team | J19: =VLOOKUP(C19,'Sales Team'!A$1:D$6,4,0) -> OnlineMarketing/Corporate Negotiate/Patnership Contract | K19: =VLOOKUP(B19,'Patner Store'!A$1:F$51,2,0) -> Surya Sport | L19: =VLOOKUP(B19,'Patner Store'!A$1:F$51,3,0) -> Retail | M19: =VLOOKUP(B19,'Patner Store'!A$1:F$51,4,0) -> Kalimantan | N19: =VLOOKUP(B19,'Patner Store'!A$1:F$51,5,0) -> South Kalimantan
A20: SO0019 | B20: PS0020 | C20: ST0004 | D20: 43854 | E20: Sulawesi, Maluku, North Maluku | F20: CREDIT | G20: 301033270 | I20: =VLOOKUP(C20,'Sales Team'!A$1:C$6,2,0) -> Sales Region Sulawesi - Maluku Team | J20: =VLOOKUP(C20,'Sales Team'!A$1:D$6,4,0) -> Corporate Negotiate/Patnership Contract | K20: =VLOOKUP(B20,'Patner Store'!A$1:F$51,2,0) -> Barokah Olahraga Shop | L20: =VLOOKUP(B20,'Patner Store'!A$1:F$51,3,0) -> Retail | M20: =VLOOKUP(B20,'Patner Store'!A$1:F$51,4,0) -> Sulawesi | N20: =VLOOKUP(B20,'Patner Store'!A$1:F$51,5,0) -> North Sulawesi
A21: SO0020 | B21: PS0019 | C21: ST0005 | D21: 43856 | E21: Bali, East & West Nusa Tenggara | F21: CASH | G21: 70487380 | I21: =VLOOKUP(C21,'Sales Team'!A$1:C$6,2,0) -> Sales Region Bali - Nusa Tenggara Team | J21: =VLOOKUP(C21,'Sales Team'!A$1:D$6,4,0) -> Corporate Negotiate/Patnership Contract | K21: =VLOOKUP(B21,'Patner Store'!A$1:F$51,2,0) -> Toko olahraga Pantai | L21: =VLOOKUP(B21,'Patner Store'!A$1:F$51,3,0) -> Retail | M21: =VLOOKUP(B21,'Patner Store'!A$1:F$51,4,0) -> Nusa Tenggara | N21: =VLOOKUP(B21,'Patner Store'!A$1:F$51,5,0) -> East Nusa Tenggara
A22: SO0021 | B22: PS0037 | C22: ST0002 | D22: 43856 | E22: Java | F22: CASH | G22: 219754110 | I22: =VLOOKUP(C22,'Sales Team'!A$1:C$6,2,0) -> Sales Java Region Team | J22: =VLOOKUP(C22,'Sales Team'!A$1:D$6,4,0) -> OnlineMarketing/Corporate Negotiate/Patnership Contract | K22: =VLOOKUP(B22,'Patner Store'!A$1:F$51,2,0) -> Toko Joko Sport | L22: =VLOOKUP(B22,'Patner Store'!A$1:F$51,3,0) -> Retail | M22: =VLOOKUP(B22,'Patner Store'!A$1:F$51,4,0) -> Java | N22: =VLOOKUP(B22,'Patner Store'!A$1:F$51,5,0) -> East Java
A23: SO0022 | B23: PS0018 | C23: ST0002 | D23: 43856 | E23: Java | F23: CREDIT | G23: 473835924 | H23: The product is unavailable from the vendor or there has been a product replacement | I23: =VLOOKUP(C23,'Sales Team'!A$1:C$6,2,0) -> Sales Java Region Team | J23: =VLOOKUP(C23,'Sales Team'!A$1:D$6,4,0) -> OnlineMarketing/Corporate Negotiate/Patnership Contract | K23: =VLOOKUP(B23,'Patner Store'!A$1:F$51,2,0) -> Sport Jogja City | L23: =VLOOKUP(B23,'Patner Store'!A$1:F$51,3,0) -> Distributor | M23: =VLOOKUP(B23,'Patner Store'!A$1:F$51,4,0) -> Java | N23: =VLOOKUP(B23,'Patner Store'!A$1:F$51,5,0) -> Jogjakarta
A24: SO0023 | B24: PS0013 | C24: ST0001 | D24: 43857 | E24: Jakarta | F24: CASH | G24: 177937976 | I24: =VLOOKUP(C24,'Sales Team'!A$1:C$6,2,0) -> Online Sales Team | J24: =VLOOKUP(C24,'Sales Team'!A$1:D$6,4,0) -> OnlineMarketing | K24: =VLOOKUP(B24,'Patner Store'!A$1:F$51,2,0) -> Playing Outdoor | L24: =VLOOKUP(B24,'Patner Store'!A$1:F$51,3,0) -> Retail | M24: =VLOOKUP(B24,'Patner Store'!A$1:F$51,4,0) -> Java | N24: =VLOOKUP(B24,'Patner Store'!A$1:F$51,5,0) -> Jakarta
A25: SO0024 | B25: PS0040 | C25: ST0003 | D25: 43859 | E25: Sumatera & Kalimantan | F25: CASH | G25: 43468350 | I25: =VLOOKUP(C25,'Sales Team'!A$1:C$6,2,0) -> Sales Sumatera -Kalimantan Region Team | J25: =VLOOKUP(C25,'Sales Team'!A$1:D$6,4,0) -> OnlineMarketing/Corporate Negotiate/Patnership Contract | K25: =VLOOKUP(B25,'Patner Store'!A$1:F$51,2,0) -> Olahraga Gemilang | L25: =VLOOKUP(B25,'Patner Store'!A$1:F$51,3,0) -> Retail | M25: =VLOOKUP(B25,'Patner Store'!A$1:F$51,4,0) -> Kalimantan | N25: =VLOOKUP(B25,'Patner Store'!A$1:F$51,5,0) -> Central Kalimantan
A26: SO0025 | B26: PS0034 | C26: ST0001 | D26: 43860 | E26: Jakarta | F26: CASH | G26: 72692150 | I26: =VLOOKUP(C26,'Sales Team'!A$1:C$6,2,0) -> Online Sales Team | J26: =VLOOKUP(C26,'Sales Team'!A$1:D$6,4,0) -> OnlineMarketing | K26: =VLOOKUP(B26,'Patner Store'!A$1:F$51,2,0) -> Active Sport | L26: =VLOOKUP(B26,'Patner Store'!A$1:F$51,3,0) -> Retail | M26: =VLOOKUP(B26,'Patner Store'!A$1:F$51,4,0) -> Java | N26: =VLOOKUP(B26,'Patner Store'!A$1:F$51,5,0) -> Jakarta
A27: SO0026 | B27: PS0021 | C27: ST0001 | D27: 43861 | E27: Jakarta | F27: CASH | G27: 249589510 | H27: The product is unavailable from the vendor or there has been a product replacement | I27: =VLOOKUP(C27,'Sales Team'!A$1:C$6,2,0) -> Online Sales Team | J27: =VLOOKUP(C27,'Sales Team'!A$1:D$6,4,0) -> OnlineMarketing | K27: =VLOOKUP(B27,'Patner Store'!A$1:F$51,2,0) -> SportArt88 | L27: =VLOOKUP(B27,'Patner Store'!A$1:F$51,3,0) -> Retail | M27: =VLOOKUP(B27,'Patner Store'!A$1:F$51,4,0) -> Java | N27: =VLOOKUP(B27,'Patner Store'!A$1:F$51,5,0) -> Jakarta
A28: SO0027 | B28: PS0047 | C28: ST0001 | D28: 43861 | E28: Jakarta | F28: CREDIT | G28: 665340650 | H28: transaction as agreed with the vendor | I28: =VLOOKUP(C28,'Sales Team'!A$1:C$6,2,0) -> Online Sales Team | J28: =VLOOKUP(C28,'Sales Team'!A$1:D$6,4,0) -> OnlineMarketing | K28: =VLOOKUP(B28,'Patner Store'!A$1:F$51,2,0) -> Power Play | L28: =VLOOKUP(B28,'Patner Store'!A$1:F$51,3,0) -> Retail | M28: =VLOOKUP(B28,'Patner Store'!A$1:F$51,4,0) -> Java | N28: =VLOOKUP(B28,'Patner Store'!A$1:F$51,5,0) -> Jakarta
A29: SO0028 | B29: PS0035 | C29: ST0004 | D29: 43866 | E29: Sulawesi, Maluku, North Maluku | F29: CASH | G29: 110695360 | H29: Partner Store canceled the order | I29: =VLOOKUP(C29,'Sales Team'!A$1:C$6,2,0) -> Sales Region Sulawesi - Maluku Team | J29: =VLOOKUP(C29,'Sales Team'!A$1:D$6,4,0) -> Corporate Negotiate/Patnership Contract | K29: =VLOOKUP(B29,'Patner Store'!A$1:F$51,2,0) -> Toko Olahraga Lengkap | L29: =VLOOKUP(B29,'Patner Store'!A$1:F$51,3,0) -> Retail | M29: =VLOOKUP(B29,'Patner Store'!A$1:F$51,4,0) -> Maluku | N29: =VLOOKUP(B29,'Patner Store'!A$1:F$51,5,0) -> Maluku
A30: SO0029 | B30: PS0028 | C30: ST0005 | D30: 43866 | E30: Bali, East & West Nusa Tenggara | F30: CASH | G30: 48219680 | I30: =VLOOKUP(C30,'Sales Team'!A$1:C$6,2,0) -> Sales Region Bali - Nusa Tenggara Team | J30: =VLOOKUP(C30,'Sales Team'!A$1:D$6,4,0) -> Corporate Negotiate/Patnership Contract | K30: =VLOOKUP(B30,'Patner Store'!A$1:F$51,2,0) -> Toko SportNesia | L30: =VLOOKUP(B30,'Patner Store'!A$1:F$51,3,0) -> Retail | M30: =VLOOKUP(B30,'Patner Store'!A$1:F$51,4,0) -> Nusa Tenggara | N30: =VLOOKUP(B30,'Patner Store'!A$1:F$51,5,0) -> East Nusa Tenggara
A31: SO0030 | B31: PS0022 | C31: ST0004 | D31: 43868 | E31: Sulawesi, Maluku, North Maluku | F31: CASH | G31: 80974010 | I31: =VLOOKUP(C31,'Sales Team'!A$1:C$6,2,0) -> Sales Region Sulawesi - Maluku Team | J31: =VLOOKUP(C31,'Sales Team'!A$1:D$6,4,0) -> Corporate Negotiate/Patnership Contract | K31: =VLOOKUP(B31,'Patner Store'!A$1:F$51,2,0) -> Sport Kita Store | L31: =VLOOKUP(B31,'Patner Store'!A$1:F$51,3,0) -> Retail | M31: =VLOOKUP(B31,'Patner Store'!A$1:F$51,4,0) -> North Maluku | N31: =VLOOKUP(B31,'Patner Store'!A$1:F$51,5,0) -> North Maluku
A32: SO0031 | B32: PS0007 | C32: ST0001 | D32: 43874 | E32: Jakarta | F32: CASH | G32: 21634158 | H32: The transaction agreement has undergone changes | I32: =VLOOKUP(C32,'Sales Team'!A$1:C$6,2,0) -> Online Sales Team | J32: =VLOOKUP(C32,'Sales Team'!A$1:D$6,4,0) -> OnlineMarketing | K32: =VLOOKUP(B32,'Patner Store'!A$1:F$51,2,0) -> Twinsport.com | L32: =VLOOKUP(B32,'Patner Store'!A$1:F$51,3,0) -> Retail | M32: =VLOOKUP(B32,'Patner Store'!A$1:F$51,4,0) -> Java | N32: =VLOOKUP(B32,'Patner Store'!A$1:F$51,5,0) -> Jakarta
A33: SO0032 | B33: PS0010 | C33: ST0001 | D33: 43875 | E33: Jakarta | F33: CASH | G33: 38254350 | I33: =VLOOKUP(C33,'Sales Team'!A$1:C$6,2,0) -> Online Sales Team | J33: =VLOOKUP(C33,'Sales Team'!A$1:D$6,4,0) -> OnlineMarketing | K33: =VLOOKUP(B33,'Patner Store'!A$1:F$51,2,0) -> WorldSport.com | L33: =VLOOKUP(B33,'Patner Store'!A$1:F$51,3,0) -> Retail | M33: =VLOOKUP(B33,'Patner Store'!A$1:F$51,4,0) -> Java | N33: =VLOOKUP(B33,'Patner Store'!A$1:F$51,5,0) -> Jakarta
A34: SO0033 | B34: PS0012 | C34: ST0003 | D34: 43875 | E34: Sumatera & Kalimantan | F34: CREDIT | G34: 274768110 | H34: The transaction agreement has undergone changes | I34: =VLOOKUP(C34,'Sales Team'!A$1:C$6,2,0) -> Sales Sumatera -Kalimantan Region Team | J34: =VLOOKUP(C34,'Sales Team'!A$1:D$6,4,0) -> OnlineMarketing/Corporate Negotiate/Patnership Contract | K34: =VLOOKUP(B34,'Patner Store'!A$1:F$51,2,0) -> Adi Shop | L34: =VLOOKUP(B34,'Patner Store'!A$1:F$51,3,0) -> Retail | M34: =VLOOKUP(B34,'Patner Store'!A$1:F$51,4,0) -> Kalimantan | N34: =VLOOKUP(B34,'Patner Store'!A$1:F$51,5,0) -> South Kalimantan
A35: SO0034 | B35: PS0001 | C35: ST0005 | D35: 43876 | E35: Bali, East & West Nusa Tenggara | F35: CASH | G35: 156249110 | I35: =VLOOKUP(C35,'Sales Team'!A$1:C$6,2,0) -> Sales Region Bali - Nusa Tenggara Team | J35: =VLOOKUP(C35,'Sales Team'!A$1:D$6,4,0) -> Corporate Negotiate/Patnership Contract | K35: =VLOOKUP(B35,'Patner Store'!A$1:F$51,2,0) -> Sport Nation | L35: =VLOOKUP(B35,'Patner Store'!A$1:F$51,3,0) -> Distributor | M35: =VLOOKUP(B35,'Patner Store'!A$1:F$51,4,0) -> Bali | N35: =VLOOKUP(B35,'Patner Store'!A$1:F$51,5,0) -> Bali
A36: SO0035 | B36: PS0033 | C36: ST0005 | D36: 43877 | E36: Bali, East & West Nusa Tenggara | F36: CREDIT | G36: 473491910 | I36: =VLOOKUP(C36,'Sales Team'!A$1:C$6,2,0) -> Sales Region Bali - Nusa Tenggara Team | J36: =VLOOKUP(C36,'Sales Team'!A$1:D$6,4,0) -> Corporate Negotiate/Patnership Contract | K36: =VLOOKUP(B36,'Patner Store'!A$1:F$51,2,0) -> Toko Olahraga NTT | L36: =VLOOKUP(B36,'Patner Store'!A$1:F$51,3,0) -> Retail | M36: =VLOOKUP(B36,'Patner Store'!A$1:F$51,4,0) -> Nusa Tenggara | N36: =VLOOKUP(B36,'Patner Store'!A$1:F$51,5,0) -> East Nusa Tenggara
A37: SO0036 | B37: PS0034 | C37: ST0001 | D37: 43878 | E37: Jakarta | F37: CREDIT | G37: 376525700 | I37: =VLOOKUP(C37,'Sales Team'!A$1:C$6,2,0) -> Online Sales Team | J37: =VLOOKUP(C37,'Sales Team'!A$1:D$6,4,0) -> OnlineMarketing | K37: =VLOOKUP(B37,'Patner Store'!A$1:F$51,2,0) -> Active Sport | L37: =VLOOKUP(B37,'Patner Store'!A$1:F$51,3,0) -> Retail | M37: =VLOOKUP(B37,'Patner Store'!A$1:F$51,4,0) -> Java | N37: =VLOOKUP(B37,'Patner Store'!A$1:F$51,5,0) -> Jakarta
A38: SO0037 | B38: PS0028 | C38: ST0005 | D38: 43881 | E38: Bali, East & West Nusa Tenggara | F38: CREDIT | G38: 1038581420 | H38: transaction as agreed with the vendor | I38: =VLOOKUP(C38,'Sales Team'!A$1:C$6,2,0) -> Sales Region Bali - Nusa Tenggara Team | J38: =VLOOKUP(C38,'Sales Team'!A$1:D$6,4,0) -> Corporate Negotiate/Patnership Contract | K38: =VLOOKUP(B38,'Patner Store'!A$1:F$51,2,0) -> Toko SportNesia | L38: =VLOOKUP(B38,'Patner Store'!A$1:F$51,3,0) -> Retail | M38: =VLOOKUP(B38,'Patner Store'!A$1:F$51,4,0) -> Nusa Tenggara | N38: =VLOOKUP(B38,'Patner Store'!A$1:F$51,5,0) -> East Nusa Tenggara
A39: SO0038 | B39: PS0036 | C39: ST0005 | D39: 43882 | E39: Bali, East & West Nusa Tenggara | F39: CASH | G39: 130531820 | I39: =VLOOKUP(C39,'Sales Team'!A$1:C$6,2,0) -> Sales Region Bali - Nusa Tenggara Team | J39: =VLOOKUP(C39,'Sales Team'!A$1:D$6,4,0) -> Corporate Negotiate/Patnership Contract | K39: =VLOOKUP(B39,'Patner Store'!A$1:F$51,2,0) -> Nusantara Sport | L39: =VLOOKUP(B39,'Patner Store'!A$1:F$51,3,0) -> Retail | M39: =VLOOKUP(B39,'Patner Store'!A$1:F$51,4,0) -> Nusa Tenggara | N39: =VLOOKUP(B39,'Patner Store'!A$1:F$51,5,0) -> West Nusa Tenggara
A40: SO0039 | B40: PS0013 | C40: ST0001 | D40: 43883 | E40: Jakarta | F40: CREDIT | G40: 1115480621 | H40: transaction as agreed with the vendor | I40: =VLOOKUP(C40,'Sales Team'!A$1:C$6,2,0) -> Online Sales Team | J40: =VLOOKUP(C40,'Sales Team'!A$1:D$6,4,0) -> OnlineMarketing | K40: =VLOOKUP(B40,'Patner Store'!A$1:F$51,2,0) -> Playing Outdoor | L40: =VLOOKUP(B40,'Patner Store'!A$1:F$51,3,0) -> Retail | M40: =VLOOKUP(B40,'Patner Store'!A$1:F$51,4,0) -> Java | N40: =VLOOKUP(B40,'Patner Store'!A$1:F$51,5,0) -> Jakarta
A41: SO0040 | B41: PS0018 | C41: ST0002 | D41: 43885 | E41: Java | F41: CREDIT | G41: 348772960 | I41: =VLOOKUP(C41,'Sales Team'!A$1:C$6,2,0) -> Sales Java Region Team | J41: =VLOOKUP(C41,'Sales Team'!A$1:D$6,4,0) -> OnlineMarketing/Corporate Negotiate/Patnership Contract | K41: =VLOOKUP(B41,'Patner Store'!A$1:F$51,2,0) -> Sport Jogja City | L41: =VLOOKUP(B41,'Patner Store'!A$1:F$51,3,0) -> Distributor | M41: =VLOOKUP(B41,'Patner Store'!A$1:F$51,4,0) -> Java | N41: =VLOOKUP(B41,'Patner Store'!A$1:F$51,5,0) -> Jogjakarta
A42: SO0041 | B42: PS0033 | C42: ST0005 | D42: 43886 | E42: Bali, East & West Nusa Tenggara | F42: CREDIT | G42: 771270590 | I42: =VLOOKUP(C42,'Sales Team'!A$1:C$6,2,0) -> Sales Region Bali - Nusa Tenggara Team | J42: =VLOOKUP(C42,'Sales Team'!A$1:D$6,4,0) -> Corporate Negotiate/Patnership Contract | K42: =VLOOKUP(B42,'Patner Store'!A$1:F$51,2,0) -> Toko Olahraga NTT | L42: =VLOOKUP(B42,'Patner Store'!A$1:F$51,3,0) -> Retail | M42: =VLOOKUP(B42,'Patner Store'!A$1:F$51,4,0) -> Nusa Tenggara | N42: =VLOOKUP(B42,'Patner Store'!A$1:F$51,5,0) -> East Nusa Tenggara
A43: SO0042 | B43: PS0030 | C43: ST0004 | D43: 43887 | E43: Sulawesi, Maluku, North Maluku | F43: CREDIT | G43: 536592260 | I43: =VLOOKUP(C43,'Sales Team'!A$1:C$6,2,0) -> Sales Region Sulawesi - Maluku Team | J43: =VLOOKUP(C43,'Sales Team'!A$1:D$6,4,0) -> Corporate Negotiate/Patnership Contract | K43: =VLOOKUP(B43,'Patner Store'!A$1:F$51,2,0) -> KakaSport | L43: =VLOOKUP(B43,'Patner Store'!A$1:F$51,3,0) -> Retail | M43: =VLOOKUP(B43,'Patner Store'!A$1:F$51,4,0) -> Maluku | N43: =VLOOKUP(B43,'Patner Store'!A$1:F$51,5,0) -> Maluku
A44: SO0043 | B44: PS0013 | C44: ST0001 | D44: 43887 | E44: Jakarta | F44: CASH | G44: 123668650 | I44: =VLOOKUP(C44,'Sales Team'!A$1:C$6,2,0) -> Online Sales Team | J44: =VLOOKUP(C44,'Sales Team'!A$1:D$6,4,0) -> OnlineMarketing | K44: =VLOOKUP(B44,'Patner Store'!A$1:F$51,2,0) -> Playing Outdoor | L44: =VLOOKUP(B44,'Patner Store'!A$1:F$51,3,0) -> Retail | M44: =VLOOKUP(B44,'Patner Store'!A$1:F$51,4,0) -> Java | N44: =VLOOKUP(B44,'Patner Store'!A$1:F$51,5,0) -> Jakarta
A45: SO0044 | B45: PS0019 | C45: ST0005 | D45: 43887 | E45: Bali, East & West Nusa Tenggara | F45: CREDIT | G45: 1067431930 | I45: =VLOOKUP(C45,'Sales Team'!A$1:C$6,2,0) -> Sales Region Bali - Nusa Tenggara Team | J45: =VLOOKUP(C45,'Sales Team'!A$1:D$6,4,0) -> Corporate Negotiate/Patnership Contract | K45: =VLOOKUP(B45,'Patner Store'!A$1:F$51,2,0) -> Toko olahraga Pantai | L45: =VLOOKUP(B45,'Patner Store'!A$1:F$51,3,0) -> Retail | M45: =VLOOKUP(B45,'Patner Store'!A$1:F$51,4,0) -> Nusa Tenggara | N45: =VLOOKUP(B45,'Patner Store'!A$1:F$51,5,0) -> East Nusa Tenggara
A46: SO0045 | B46: PS0023 | C46: ST0003 | D46: 43888 | E46: Sumatera & Kalimantan | F46: CASH | G46: 217941590 | H46: The transaction agreement has undergone changes | I46: =VLOOKUP(C46,'Sales Team'!A$1:C$6,2,0) -> Sales Sumatera -Kalimantan Region Team | J46: =VLOOKUP(C46,'Sales Team'!A$1:D$6,4,0) -> OnlineMarketing/Corporate Negotiate/Patnership Contract | K46: =VLOOKUP(B46,'Patner Store'!A$1:F$51,2,0) -> Gudang Sport Center | L46: =VLOOKUP(B46,'Patner Store'!A$1:F$51,3,0) -> Retail | M46: =VLOOKUP(B46,'Patner Store'!A$1:F$51,4,0) -> Kalimantan | N46: =VLOOKUP(B46,'Patner Store'!A$1:F$51,5,0) -> Central Kalimantan
A47: SO0046 | B47: PS0007 | C47: ST0001 | D47: 43889 | E47: Jakarta | F47: CREDIT | G47: 311577560 | I47: =VLOOKUP(C47,'Sales Team'!A$1:C$6,2,0) -> Online Sales Team | J47: =VLOOKUP(C47,'Sales Team'!A$1:D$6,4,0) -> OnlineMarketing | K47: =VLOOKUP(B47,'Patner Store'!A$1:F$51,2,0) -> Twinsport.com | L47: =VLOOKUP(B47,'Patner Store'!A$1:F$51,3,0) -> Retail | M47: =VLOOKUP(B47,'Patner Store'!A$1:F$51,4,0) -> Java | N47: =VLOOKUP(B47,'Patner Store'!A$1:F$51,5,0) -> Jakarta
A48: SO0047 | B48: PS0001 | C48: ST0005 | D48: 43889 | E48: Bali, East & West Nusa Tenggara | F48: CREDIT | G48: 1147156860 | H48: transaction as agreed with the vendor | I48: =VLOOKUP(C48,'Sales Team'!A$1:C$6,2,0) -> Sales Region Bali - Nusa Tenggara Team | J48: =VLOOKUP(C48,'Sales Team'!A$1:D$6,4,0) -> Corporate Negotiate/Patnership Contract | K48: =VLOOKUP(B48,'Patner Store'!A$1:F$51,2,0) -> Sport Nation | L48: =VLOOKUP(B48,'Patner Store'!A$1:F$51,3,0) -> Distributor | M48: =VLOOKUP(B48,'Patner Store'!A$1:F$51,4,0) -> Bali | N48: =VLOOKUP(B48,'Patner Store'!A$1:F$51,5,0) -> Bali
A49: SO0048 | B49: PS0029 | C49: ST0004 | D49: 43889 | E49: Sulawesi, Maluku, North Maluku | F49: CASH | G49: 240900870 | I49: =VLOOKUP(C49,'Sales Team'!A$1:C$6,2,0) -> Sales Region Sulawesi - Maluku Team | J49: =VLOOKUP(C49,'Sales Team'!A$1:D$6,4,0) -> Corporate Negotiate/Patnership Contract | K49: =VLOOKUP(B49,'Patner Store'!A$1:F$51,2,0) -> Mama Sport | L49: =VLOOKUP(B49,'Patner Store'!A$1:F$51,3,0) -> Retail | M49: =VLOOKUP(B49,'Patner Store'!A$1:F$51,4,0) -> North Maluku | N49: =VLOOKUP(B49,'Patner Store'!A$1:F$51,5,0) -> North Maluku
A50: SO0049 | B50: PS0048 | C50: ST0003 | D50: 43889 | E50: Sumatera & Kalimantan | F50: CASH | G50: 37095840 | I50: =VLOOKUP(C50,'Sales Team'!A$1:C$6,2,0) -> Sales Sumatera -Kalimantan Region Team | J50: =VLOOKUP(C50,'Sales Team'!A$1:D$6,4,0) -> OnlineMarketing/Corporate Negotiate/Patnership Contract | K50: =VLOOKUP(B50,'Patner Store'!A$1:F$51,2,0) -> Toko Olahraga Mandiri | L50: =VLOOKUP(B50,'Patner Store'!A$1:F$51,3,0) -> Retail | M50: =VLOOKUP(B50,'Patner Store'!A$1:F$51,4,0) -> Kalimantan | N50: =VLOOKUP(B50,'Patner Store'!A$1:F$51,5,0) -> South Kalimantan
A51: SO0050 | B51: PS0010 | C51: ST0001 | D51: 43890 | E51: Jakarta | F51: CASH | G51: 129203710 | H51: The product is unavailable from the vendor or there has been a product replacement | I51: =VLOOKUP(C51,'Sales Team'!A$1:C$6,2,0) -> Online Sales Team | J51: =VLOOKUP(C51,'Sales Team'!A$1:D$6,4,0) -> OnlineMarketing | K51: =VLOOKUP(B51,'Patner Store'!A$1:F$51,2,0) -> WorldSport.com | L51: =VLOOKUP(B51,'Patner Store'!A$1:F$51,3,0) -> Retail | M51: =VLOOKUP(B51,'Patner Store'!A$1:F$51,4,0) -> Java | N51: =VLOOKUP(B51,'Patner Store'!A$1:F$51,5,0) -> Jakarta
A52: SO0051 | B52: PS0034 | C52: ST0001 | D52: 43890 | E52: Jakarta | F52: CASH | G52: 76098970 | I52: =VLOOKUP(C52,'Sales Team'!A$1:C$6,2,0) -> Online Sales Team | J52: =VLOOKUP(C52,'Sales Team'!A$1:D$6,4,0) -> OnlineMarketing | K52: =VLOOKUP(B52,'Patner Store'!A$1:F$51,2,0) -> Active Sport | L52: =VLOOKUP(B52,'Patner Store'!A$1:F$51,3,0) -> Retail | M52: =VLOOKUP(B52,'Patner Store'!A$1:F$51,4,0) -> Java | N52: =VLOOKUP(B52,'Patner Store'!A$1:F$51,5,0) -> Jakarta
A53: SO0052 | B53: PS0024 | C53: ST0001 | D53: 43892 | E53: Jakarta | F53: CREDIT | G53: 465515470 | H53: The transaction agreement has undergone changes | I53: =VLOOKUP(C53,'Sales Team'!A$1:C$6,2,0) -> Online Sales Team | J53: =VLOOKUP(C53,'Sales Team'!A$1:D$6,4,0) -> OnlineMarketing | K53: =VLOOKUP(B53,'Patner Store'!A$1:F$51,2,0) -> SportChampion10 | L53: =VLOOKUP(B53,'Patner Store'!A$1:F$51,3,0) -> Retail | M53: =VLOOKUP(B53,'Patner Store'!A$1:F$51,4,0) -> Java | N53: =VLOOKUP(B53,'Patner Store'!A$1:F$51,5,0) -> Jakarta
A54: SO0053 | B54: PS0048 | C54: ST0003 | D54: 43894 | E54: Sumatera & Kalimantan | F54: CREDIT | G54: 464354520 | I54: =VLOOKUP(C54,'Sales Team'!A$1:C$6,2,0) -> Sales Sumatera -Kalimantan Region Team | J54: =VLOOKUP(C54,'Sales Team'!A$1:D$6,4,0) -> OnlineMarketing/Corporate Negotiate/Patnership Contract | K54: =VLOOKUP(B54,'Patner Store'!A$1:F$51,2,0) -> Toko Olahraga Mandiri | L54: =VLOOKUP(B54,'Patner Store'!A$1:F$51,3,0) -> Retail | M54: =VLOOKUP(B54,'Patner Store'!A$1:F$51,4,0) -> Kalimantan | N54: =VLOOKUP(B54,'Patner Store'!A$1:F$51,5,0) -> South Kalimantan
A55: SO0054 | B55: PS0013 | C55: ST0001 | D55: 43896 | E55: Jakarta | F55: CREDIT | G55: 284343460 | I55: =VLOOKUP(C55,'Sales Team'!A$1:C$6,2,0) -> Online Sales Team | J55: =VLOOKUP(C55,'Sales Team'!A$1:D$6,4,0) -> OnlineMarketing | K55: =VLOOKUP(B55,'Patner Store'!A$1:F$51,2,0) -> Playing Outdoor | L55: =VLOOKUP(B55,'Patner Store'!A$1:F$51,3,0) -> Retail | M55: =VLOOKUP(B55,'Patner Store'!A$1:F$51,4,0) -> Java | N55: =VLOOKUP(B55,'Patner Store'!A$1:F$51,5,0) -> Jakarta
A56: SO0055 | B56: PS0002 | C56: ST0002 | D56: 43898 | E56: Java | F56: CASH | G56: 77442120 | I56: =VLOOKUP(C56,'Sales Team'!A$1:C$6,2,0) -> Sales Java Region Team | J56: =VLOOKUP(C56,'Sales Team'!A$1:D$6,4,0) -> OnlineMarketing/Corporate Negotiate/Patnership Contract | K56: =VLOOKUP(B56,'Patner Store'!A$1:F$51,2,0) -> TokoSport | L56: =VLOOKUP(B56,'Patner Store'!A$1:F$51,3,0) -> Retail | M56: =VLOOKUP(B56,'Patner Store'!A$1:F$51,4,0) -> Java | N56: =VLOOKUP(B56,'Patner Store'!A$1:F$51,5,0) -> East Java
A57: SO0056 | B57: PS0044 | C57: ST0004 | D57: 43898 | E57: Sulawesi, Maluku, North Maluku | F57: CREDIT | G57: 382553210 | I57: =VLOOKUP(C57,'Sales Team'!A$1:C$6,2,0) -> Sales Region Sulawesi - Maluku Team | J57: =VLOOKUP(C57,'Sales Team'!A$1:D$6,4,0) -> Corporate Negotiate/Patnership Contract | K57: =VLOOKUP(B57,'Patner Store'!A$1:F$51,2,0) -> Toko Rezeki Olahraga | L57: =VLOOKUP(B57,'Patner Store'!A$1:F$51,3,0) -> Retail | M57: =VLOOKUP(B57,'Patner Store'!A$1:F$51,4,0) -> Sulawesi | N57: =VLOOKUP(B57,'Patner Store'!A$1:F$51,5,0) -> North Sulawesi
A58: SO0057 | B58: PS0034 | C58: ST0001 | D58: 43899 | E58: Jakarta | F58: CASH | G58: 61818400 | I58: =VLOOKUP(C58,'Sales Team'!A$1:C$6,2,0) -> Online Sales Team | J58: =VLOOKUP(C58,'Sales Team'!A$1:D$6,4,0) -> OnlineMarketing | K58: =VLOOKUP(B58,'Patner Store'!A$1:F$51,2,0) -> Active Sport | L58: =VLOOKUP(B58,'Patner Store'!A$1:F$51,3,0) -> Retail | M58: =VLOOKUP(B58,'Patner Store'!A$1:F$51,4,0) -> Java | N58: =VLOOKUP(B58,'Patner Store'!A$1:F$51,5,0) -> Jakarta
A59: SO0058 | B59: PS0038 | C59: ST0004 | D59: 43900 | E59: Sulawesi, Maluku, North Maluku | F59: CREDIT | G59: 757026440 | I59: =VLOOKUP(C59,'Sales Team'!A$1:C$6,2,0) -> Sales Region Sulawesi - Maluku Team | J59: =VLOOKUP(C59,'Sales Team'!A$1:D$6,4,0) -> Corporate Negotiate/Patnership Contract | K59: =VLOOKUP(B59,'Patner Store'!A$1:F$51,2,0) -> Salam Olahraga | L59: =VLOOKUP(B59,'Patner Store'!A$1:F$51,3,0) -> Retail | M59: =VLOOKUP(B59,'Patner Store'!A$1:F$51,4,0) -> Maluku | N59: =VLOOKUP(B59,'Patner Store'!A$1:F$51,5,0) -> Maluku
A60: SO0059 | B60: PS0046 | C60: ST0003 | D60: 43900 | E60: Sumatera & Kalimantan | F60: CREDIT | G60: 312940260 | I60: =VLOOKUP(C60,'Sales Team'!A$1:C$6,2,0) -> Sales Sumatera -Kalimantan Region Team | J60: =VLOOKUP(C60,'Sales Team'!A$1:D$6,4,0) -> OnlineMarketing/Corporate Negotiate/Patnership Contract | K60: =VLOOKUP(B60,'Patner Store'!A$1:F$51,2,0) -> Markas Olahraga | L60: =VLOOKUP(B60,'Patner Store'!A$1:F$51,3,0) -> Retail | M60: =VLOOKUP(B60,'Patner Store'!A$1:F$51,4,0) -> Kalimantan | N60: =VLOOKUP(B60,'Patner Store'!A$1:F$51,5,0) -> South Kalimantan
A61: SO0060 | B61: PS0006 | C61: ST0003 | D61: 43903 | E61: Sumatera & Kalimantan | F61: CREDIT | G61: 331282420 | I61: =VLOOKUP(C61,'Sales Team'!A$1:C$6,2,0) -> Sales Sumatera -Kalimantan Region Team | J61: =VLOOKUP(C61,'Sales Team'!A$1:D$6,4,0) -> OnlineMarketing/Corporate Negotiate/Patnership Contract | K61: =VLOOKUP(B61,'Patner Store'!A$1:F$51,2,0) -> Arena Sport Shop | L61: =VLOOKUP(B61,'Patner Store'!A$1:F$51,3,0) -> Retail | M61: =VLOOKUP(B61,'Patner Store'!A$1:F$51,4,0) -> Kalimantan | N61: =VLOOKUP(B61,'Patner Store'!A$1:F$51,5,0) -> Central Kalimantan
A62: SO0061 | B62: PS0045 | C62: ST0005 | D62: 43903 | E62: Bali, East & West Nusa Tenggara | F62: CREDIT | G62: 398127800 | H62: Partner Store canceled the order | I62: =VLOOKUP(C62,'Sales Team'!A$1:C$6,2,0) -> Sales Region Bali - Nusa Tenggara Team | J62: =VLOOKUP(C62,'Sales Team'!A$1:D$6,4,0) -> Corporate Negotiate/Patnership Contract | K62: =VLOOKUP(B62,'Patner Store'!A$1:F$51,2,0) -> Toko Olahraga NTB | L62: =VLOOKUP(B62,'Patner Store'!A$1:F$51,3,0) -> Retail | M62: =VLOOKUP(B62,'Patner Store'!A$1:F$51,4,0) -> Nusa Tenggara | N62: =VLOOKUP(B62,'Patner Store'!A$1:F$51,5,0) -> West Nusa Tenggara
A63: SO0062 | B63: PS0050 | C63: ST0004 | D63: 43904 | E63: Sulawesi, Maluku, North Maluku | F63: CASH | G63: 157292976 | H63: The transaction agreement has undergone changes | I63: =VLOOKUP(C63,'Sales Team'!A$1:C$6,2,0) -> Sales Region Sulawesi - Maluku Team | J63: =VLOOKUP(C63,'Sales Team'!A$1:D$6,4,0) -> Corporate Negotiate/Patnership Contract | K63: =VLOOKUP(B63,'Patner Store'!A$1:F$51,2,0) -> Toko Peralatan Olahraga | L63: =VLOOKUP(B63,'Patner Store'!A$1:F$51,3,0) -> Retail | M63: =VLOOKUP(B63,'Patner Store'!A$1:F$51,4,0) -> Maluku | N63: =VLOOKUP(B63,'Patner Store'!A$1:F$51,5,0) -> Maluku
A64: SO0063 | B64: PS0015 | C64: ST0004 | D64: 43905 | E64: Sulawesi, Maluku, North Maluku | F64: CASH | G64: 259271600 | H64: Partner Store canceled the order | I64: =VLOOKUP(C64,'Sales Team'!A$1:C$6,2,0) -> Sales Region Sulawesi - Maluku Team | J64: =VLOOKUP(C64,'Sales Team'!A$1:D$6,4,0) -> Corporate Negotiate/Patnership Contract | K64: =VLOOKUP(B64,'Patner Store'!A$1:F$51,2,0) -> Toko Olahraga Satu | L64: =VLOOKUP(B64,'Patner Store'!A$1:F$51,3,0) -> Retail | M64: =VLOOKUP(B64,'Patner Store'!A$1:F$51,4,0) -> North Maluku | N64: =VLOOKUP(B64,'Patner Store'!A$1:F$51,5,0) -> North Maluku
A65: SO0064 | B65: PS0004 | C65: ST0001 | D65: 43906 | E65: Jakarta | F65: CREDIT | G65: 750000080 | H65: The transaction agreement has undergone changes | I65: =VLOOKUP(C65,'Sales Team'!A$1:C$6,2,0) -> Online Sales Team | J65: =VLOOKUP(C65,'Sales Team'!A$1:D$6,4,0) -> OnlineMarketing | K65: =VLOOKUP(B65,'Patner Store'!A$1:F$51,2,0) -> Sport Line Indonesia | L65: =VLOOKUP(B65,'Patner Store'!A$1:F$51,3,0) -> Retail | M65: =VLOOKUP(B65,'Patner Store'!A$1:F$51,4,0) -> Java | N65: =VLOOKUP(B65,'Patner Store'!A$1:F$51,5,0) -> Jakarta
A66: SO0065 | B66: PS0043 | C66: ST0004 | D66: 43907 | E66: Sulawesi, Maluku, North Maluku | F66: CREDIT | G66: 919658870 | H66: transaction as agreed with the vendor | I66: =VLOOKUP(C66,'Sales Team'!A$1:C$6,2,0) -> Sales Region Sulawesi - Maluku Team | J66: =VLOOKUP(C66,'Sales Team'!A$1:D$6,4,0) -> Corporate Negotiate/Patnership Contract | K66: =VLOOKUP(B66,'Patner Store'!A$1:F$51,2,0) -> SportMania Store | L66: =VLOOKUP(B66,'Patner Store'!A$1:F$51,3,0) -> Retail | M66: =VLOOKUP(B66,'Patner Store'!A$1:F$51,4,0) -> North Maluku | N66: =VLOOKUP(B66,'Patner Store'!A$1:F$51,5,0) -> North Maluku
A67: SO0066 | B67: PS0023 | C67: ST0003 | D67: 43909 | E67: Sumatera & Kalimantan | F67: CASH | G67: 181153520 | I67: =VLOOKUP(C67,'Sales Team'!A$1:C$6,2,0) -> Sales Sumatera -Kalimantan Region Team | J67: =VLOOKUP(C67,'Sales Team'!A$1:D$6,4,0) -> OnlineMarketing/Corporate Negotiate/Patnership Contract | K67: =VLOOKUP(B67,'Patner Store'!A$1:F$51,2,0) -> Gudang Sport Center | L67: =VLOOKUP(B67,'Patner Store'!A$1:F$51,3,0) -> Retail | M67: =VLOOKUP(B67,'Patner Store'!A$1:F$51,4,0) -> Kalimantan | N67: =VLOOKUP(B67,'Patner Store'!A$1:F$51,5,0) -> Central Kalimantan
A68: SO0067 | B68: PS0049 | C68: ST0004 | D68: 43910 | E68: Sulawesi, Maluku, North Maluku | F68: CREDIT | G68: 299483548 | H68: The transaction agreement has undergone changes | I68: =VLOOKUP(C68,'Sales Team'!A$1:C$6,2,0) -> Sales Region Sulawesi - Maluku Team | J68: =VLOOKUP(C68,'Sales Team'!A$1:D$6,4,0) -> Corporate Negotiate/Patnership Contract | K68: =VLOOKUP(B68,'Patner Store'!A$1:F$51,2,0) -> Toko Olahraga Bersama | L68: =VLOOKUP(B68,'Patner Store'!A$1:F$51,3,0) -> Retail | M68: =VLOOKUP(B68,'Patner Store'!A$1:F$51,4,0) -> Sulawesi | N68: =VLOOKUP(B68,'Patner Store'!A$1:F$51,5,0) -> North Sulawesi
A69: SO0068 | B69: PS0039 | C69: ST0003 | D69: 43910 | E69: Sumatera & Kalimantan | F69: CASH | G69: 23910534 | I69: =VLOOKUP(C69,'Sales Team'!A$1:C$6,2,0) -> Sales Sumatera -Kalimantan Region Team | J69: =VLOOKUP(C69,'Sales Team'!A$1:D$6,4,0) -> OnlineMarketing/Corporate Negotiate/Patnership Contract | K69: =VLOOKUP(B69,'Patner Store'!A$1:F$51,2,0) -> Surya Sport | L69: =VLOOKUP(B69,'Patner Store'!A$1:F$51,3,0) -> Retail | M69: =VLOOKUP(B69,'Patner Store'!A$1:F$51,4,0) -> Kalimantan | N69: =VLOOKUP(B69,'Patner Store'!A$1:F$51,5,0) -> South Kalimantan
A70: SO0069 | B70: PS0033 | C70: ST0005 | D70: 43911 | E70: Bali, East & West Nusa Tenggara | F70: CREDIT | G70: 781515220 | I70: =VLOOKUP(C70,'Sales Team'!A$1:C$6,2,0) -> Sales Region Bali - Nusa Tenggara Team | J70: =VLOOKUP(C70,'Sales Team'!A$1:D$6,4,0) -> Corporate Negotiate/Patnership Contract | K70: =VLOOKUP(B70,'Patner Store'!A$1:F$51,2,0) -> Toko Olahraga NTT | L70: =VLOOKUP(B70,'Patner Store'!A$1:F$51,3,0) -> Retail | M70: =VLOOKUP(B70,'Patner Store'!A$1:F$51,4,0) -> Nusa Tenggara | N70: =VLOOKUP(B70,'Patner Store'!A$1:F$51,5,0) -> East Nusa Tenggara
A71: SO0070 | B71: PS0010 | C71: ST0001 | D71: 43912 | E71: Jakarta | F71: CREDIT | G71: 559930221 | I71: =VLOOKUP(C71,'Sales Team'!A$1:C$6,2,0) -> Online Sales Team | J71: =VLOOKUP(C71,'Sales Team'!A$1:D$6,4,0) -> OnlineMarketing | K71: =VLOOKUP(B71,'Patner Store'!A$1:F$51,2,0) -> WorldSport.com | L71: =VLOOKUP(B71,'Patner Store'!A$1:F$51,3,0) -> Retail | M71: =VLOOKUP(B71,'Patner Store'!A$1:F$51,4,0) -> Java | N71: =VLOOKUP(B71,'Patner Store'!A$1:F$51,5,0) -> Jakarta
A72: SO0071 | B72: PS0014 | C72: ST0003 | D72: 43914 | E72: Sumatera & Kalimantan | F72: CASH | G72: 247944360 | H72: Partner Store canceled the order | I72: =VLOOKUP(C72,'Sales Team'!A$1:C$6,2,0) -> Sales Sumatera -Kalimantan Region Team | J72: =VLOOKUP(C72,'Sales Team'!A$1:D$6,4,0) -> OnlineMarketing/Corporate Negotiate/Patnership Contract | K72: =VLOOKUP(B72,'Patner Store'!A$1:F$51,2,0) -> Sport Hub Medan | L72: =VLOOKUP(B72,'Patner Store'!A$1:F$51,3,0) -> Distributor | M72: =VLOOKUP(B72,'Patner Store'!A$1:F$51,4,0) -> Sumatera | N72: =VLOOKUP(B72,'Patner Store'!A$1:F$51,5,0) -> North Sumatera
A73: SO0072 | B73: PS0002 | C73: ST0002 | D73: 43915 | E73: Java | F73: CREDIT | G73: 494604260 | I73: =VLOOKUP(C73,'Sales Team'!A$1:C$6,2,0) -> Sales Java Region Team | J73: =VLOOKUP(C73,'Sales Team'!A$1:D$6,4,0) -> OnlineMarketing/Corporate Negotiate/Patnership Contract | K73: =VLOOKUP(B73,'Patner Store'!A$1:F$51,2,0) -> TokoSport | L73: =VLOOKUP(B73,'Patner Store'!A$1:F$51,3,0) -> Retail | M73: =VLOOKUP(B73,'Patner Store'!A$1:F$51,4,0) -> Java | N73: =VLOOKUP(B73,'Patner Store'!A$1:F$51,5,0) -> East Java
A74: SO0073 | B74: PS0006 | C74: ST0003 | D74: 43918 | E74: Sumatera & Kalimantan | F74: CREDIT | G74: 545147080 | H74: The product is unavailable from the vendor or there has been a product replacement | I74: =VLOOKUP(C74,'Sales Team'!A$1:C$6,2,0) -> Sales Sumatera -Kalimantan Region Team | J74: =VLOOKUP(C74,'Sales Team'!A$1:D$6,4,0) -> OnlineMarketing/Corporate Negotiate/Patnership Contract | K74: =VLOOKUP(B74,'Patner Store'!A$1:F$51,2,0) -> Arena Sport Shop | L74: =VLOOKUP(B74,'Patner Store'!A$1:F$51,3,0) -> Retail | M74: =VLOOKUP(B74,'Patner Store'!A$1:F$51,4,0) -> Kalimantan | N74: =VLOOKUP(B74,'Patner Store'!A$1:F$51,5,0) -> Central Kalimantan
A75: SO0074 | B75: PS0045 | C75: ST0005 | D75: 43918 | E75: Bali, East & West Nusa Tenggara | F75: CREDIT | G75: 270630790 | I75: =VLOOKUP(C75,'Sales Team'!A$1:C$6,2,0) -> Sales Region Bali - Nusa Tenggara Team | J75: =VLOOKUP(C75,'Sales Team'!A$1:D$6,4,0) -> Corporate Negotiate/Patnership Contract | K75: =VLOOKUP(B75,'Patner Store'!A$1:F$51,2,0) -> Toko Olahraga NTB | L75: =VLOOKUP(B75,'Patner Store'!A$1:F$51,3,0) -> Retail | M75: =VLOOKUP(B75,'Patner Store'!A$1:F$51,4,0) -> Nusa Tenggara | N75: =VLOOKUP(B75,'Patner Store'!A$1:F$51,5,0) -> West Nusa Tenggara
A76: SO0075 | B76: PS0047 | C76: ST0001 | D76: 43918 | E76: Jakarta | F76: CREDIT | G76: 377959410 | H76: The transaction agreement has undergone changes | I76: =VLOOKUP(C76,'Sales Team'!A$1:C$6,2,0) -> Online Sales Team | J76: =VLOOKUP(C76,'Sales Team'!A$1:D$6,4,0) -> OnlineMarketing | K76: =VLOOKUP(B76,'Patner Store'!A$1:F$51,2,0) -> Power Play | L76: =VLOOKUP(B76,'Patner Store'!A$1:F$51,3,0) -> Retail | M76: =VLOOKUP(B76,'Patner Store'!A$1:F$51,4,0) -> Java | N76: =VLOOKUP(B76,'Patner Store'!A$1:F$51,5,0) -> Jakarta
A77: SO0076 | B77: PS0044 | C77: ST0004 | D77: 43922 | E77: Sulawesi, Maluku, North Maluku | F77: CREDIT | G77: 876499000 | I77: =VLOOKUP(C77,'Sales Team'!A$1:C$6,2,0) -> Sales Region Sulawesi - Maluku Team | J77: =VLOOKUP(C77,'Sales Team'!A$1:D$6,4,0) -> Corporate Negotiate/Patnership Contract | K77: =VLOOKUP(B77,'Patner Store'!A$1:F$51,2,0) -> Toko Rezeki Olahraga | L77: =VLOOKUP(B77,'Patner Store'!A$1:F$51,3,0) -> Retail | M77: =VLOOKUP(B77,'Patner Store'!A$1:F$51,4,0) -> Sulawesi | N77: =VLOOKUP(B77,'Patner Store'!A$1:F$51,5,0) -> North Sulawesi
A78: SO0077 | B78: PS0037 | C78: ST0002 | D78: 43922 | E78: Java | F78: CASH | G78: 131974560 | I78: =VLOOKUP(C78,'Sales Team'!A$1:C$6,2,0) -> Sales Java Region Team | J78: =VLOOKUP(C78,'Sales Team'!A$1:D$6,4,0) -> OnlineMarketing/Corporate Negotiate/Patnership Contract | K78: =VLOOKUP(B78,'Patner Store'!A$1:F$51,2,0) -> Toko Joko Sport | L78: =VLOOKUP(B78,'Patner Store'!A$1:F$51,3,0) -> Retail | M78: =VLOOKUP(B78,'Patner Store'!A$1:F$51,4,0) -> Java | N78: =VLOOKUP(B78,'Patner Store'!A$1:F$51,5,0) -> East Java
A79: SO0078 | B79: PS0021 | C79: ST0001 | D79: 43923 | E79: Jakarta | F79: CREDIT | G79: 765396800 | I79: =VLOOKUP(C79,'Sales Team'!A$1:C$6,2,0) -> Online Sales Team | J79: =VLOOKUP(C79,'Sales Team'!A$1:D$6,4,0) -> OnlineMarketing | K79: =VLOOKUP(B79,'Patner Store'!A$1:F$51,2,0) -> SportArt88 | L79: =VLOOKUP(B79,'Patner Store'!A$1:F$51,3,0) -> Retail | M79: =VLOOKUP(B79,'Patner Store'!A$1:F$51,4,0) -> Java | N79: =VLOOKUP(B79,'Patner Store'!A$1:F$51,5,0) -> Jakarta
A80: SO0079 | B80: PS0021 | C80: ST0001 | D80: 43924 | E80: Jakarta | F80: CREDIT | G80: 573244800 | I80: =VLOOKUP(C80,'Sales Team'!A$1:C$6,2,0) -> Online Sales Team | J80: =VLOOKUP(C80,'Sales Team'!A$1:D$6,4,0) -> OnlineMarketing | K80: =VLOOKUP(B80,'Patner Store'!A$1:F$51,2,0) -> SportArt88 | L80: =VLOOKUP(B80,'Patner Store'!A$1:F$51,3,0) -> Retail | M80: =VLOOKUP(B80,'Patner Store'!A$1:F$51,4,0) -> Java | N80: =VLOOKUP(B80,'Patner Store'!A$1:F$51,5,0) -> Jakarta
A81: SO0080 | B81: PS0027 | C81: ST0004 | D81: 43924 | E81: Sulawesi, Maluku, North Maluku | F81: CASH | G81: 244735950 | H81: The product is unavailable from the vendor or there has been a product replacement | I81: =VLOOKUP(C81,'Sales Team'!A$1:C$6,2,0) -> Sales Region Sulawesi - Maluku Team | J81: =VLOOKUP(C81,'Sales Team'!A$1:D$6,4,0) -> Corporate Negotiate/Patnership Contract | K81: =VLOOKUP(B81,'Patner Store'!A$1:F$51,2,0) -> Destination Sport Store | L81: =VLOOKUP(B81,'Patner Store'!A$1:F$51,3,0) -> Retail | M81: =VLOOKUP(B81,'Patner Store'!A$1:F$51,4,0) -> Maluku | N81: =VLOOKUP(B81,'Patner Store'!A$1:F$51,5,0) -> Maluku
A82: SO0081 | B82: PS0041 | C82: ST0001 | D82: 43926 | E82: Jakarta | F82: CREDIT | G82: 271572380 | I82: =VLOOKUP(C82,'Sales Team'!A$1:C$6,2,0) -> Online Sales Team | J82: =VLOOKUP(C82,'Sales Team'!A$1:D$6,4,0) -> OnlineMarketing | K82: =VLOOKUP(B82,'Patner Store'!A$1:F$51,2,0) -> GilaSport.id | L82: =VLOOKUP(B82,'Patner Store'!A$1:F$51,3,0) -> Retail | M82: =VLOOKUP(B82,'Patner Store'!A$1:F$51,4,0) -> Java | N82: =VLOOKUP(B82,'Patner Store'!A$1:F$51,5,0) -> Jakarta
A83: SO0082 | B83: PS0020 | C83: ST0004 | D83: 43927 | E83: Sulawesi, Maluku, North Maluku | F83: CREDIT | G83: 490183780 | I83: =VLOOKUP(C83,'Sales Team'!A$1:C$6,2,0) -> Sales Region Sulawesi - Maluku Team | J83: =VLOOKUP(C83,'Sales Team'!A$1:D$6,4,0) -> Corporate Negotiate/Patnership Contract | K83: =VLOOKUP(B83,'Patner Store'!A$1:F$51,2,0) -> Barokah Olahraga Shop | L83: =VLOOKUP(B83,'Patner Store'!A$1:F$51,3,0) -> Retail | M83: =VLOOKUP(B83,'Patner Store'!A$1:F$51,4,0) -> Sulawesi | N83: =VLOOKUP(B83,'Patner Store'!A$1:F$51,5,0) -> North Sulawesi
A84: SO0083 | B84: PS0033 | C84: ST0005 | D84: 43927 | E84: Bali, East & West Nusa Tenggara | F84: CREDIT | G84: 276751040 | H84: The product is unavailable from the vendor or there has been a product replacement | I84: =VLOOKUP(C84,'Sales Team'!A$1:C$6,2,0) -> Sales Region Bali - Nusa Tenggara Team | J84: =VLOOKUP(C84,'Sales Team'!A$1:D$6,4,0) -> Corporate Negotiate/Patnership Contract | K84: =VLOOKUP(B84,'Patner Store'!A$1:F$51,2,0) -> Toko Olahraga NTT | L84: =VLOOKUP(B84,'Patner Store'!A$1:F$51,3,0) -> Retail | M84: =VLOOKUP(B84,'Patner Store'!A$1:F$51,4,0) -> Nusa Tenggara | N84: =VLOOKUP(B84,'Patner Store'!A$1:F$51,5,0) -> East Nusa Tenggara
A85: SO0084 | B85: PS0041 | C85: ST0001 | D85: 43929 | E85: Jakarta | F85: CASH | G85: 64066010 | I85: =VLOOKUP(C85,'Sales Team'!A$1:C$6,2,0) -> Online Sales Team | J85: =VLOOKUP(C85,'Sales Team'!A$1:D$6,4,0) -> OnlineMarketing | K85: =VLOOKUP(B85,'Patner Store'!A$1:F$51,2,0) -> GilaSport.id | L85: =VLOOKUP(B85,'Patner Store'!A$1:F$51,3,0) -> Retail | M85: =VLOOKUP(B85,'Patner Store'!A$1:F$51,4,0) -> Java | N85: =VLOOKUP(B85,'Patner Store'!A$1:F$51,5,0) -> Jakarta
A86: SO0085 | B86: PS0049 | C86: ST0004 | D86: 43932 | E86: Sulawesi, Maluku, North Maluku | F86: CASH | G86: 244066360 | I86: =VLOOKUP(C86,'Sales Team'!A$1:C$6,2,0) -> Sales Region Sulawesi - Maluku Team | J86: =VLOOKUP(C86,'Sales Team'!A$1:D$6,4,0) -> Corporate Negotiate/Patnership Contract | K86: =VLOOKUP(B86,'Patner Store'!A$1:F$51,2,0) -> Toko Olahraga Bersama | L86: =VLOOKUP(B86,'Patner Store'!A$1:F$51,3,0) -> Retail | M86: =VLOOKUP(B86,'Patner Store'!A$1:F$51,4,0) -> Sulawesi | N86: =VLOOKUP(B86,'Patner Store'!A$1:F$51,5,0) -> North Sulawesi
A87: SO0086 | B87: PS0019 | C87: ST0005 | D87: 43933 | E87: Bali, East & West Nusa Tenggara | F87: CASH | G87: 231369915 | I87: =VLOOKUP(C87,'Sales Team'!A$1:C$6,2,0) -> Sales Region Bali - Nusa Tenggara Team | J87: =VLOOKUP(C87,'Sales Team'!A$1:D$6,4,0) -> Corporate Negotiate/Patnership Contract | K87: =VLOOKUP(B87,'Patner Store'!A$1:F$51,2,0) -> Toko olahraga Pantai | L87: =VLOOKUP(B87,'Patner Store'!A$1:F$51,3,0) -> Retail | M87: =VLOOKUP(B87,'Patner Store'!A$1:F$51,4,0) -> Nusa Tenggara | N87: =VLOOKUP(B87,'Patner Store'!A$1:F$51,5,0) -> East Nusa Tenggara
A88: SO0087 | B88: PS0004 | C88: ST0001 | D88: 43934 | E88: Jakarta | F88: CASH | G88: 99405960 | H88: The product is unavailable from the vendor or there has been a product replacement | I88: =VLOOKUP(C88,'Sales Team'!A$1:C$6,2,0) -> Online Sales Team | J88: =VLOOKUP(C88,'Sales Team'!A$1:D$6,4,0) -> OnlineMarketing | K88: =VLOOKUP(B88,'Patner Store'!A$1:F$51,2,0) -> Sport Line Indonesia | L88: =VLOOKUP(B88,'Patner Store'!A$1:F$51,3,0) -> Retail | M88: =VLOOKUP(B88,'Patner Store'!A$1:F$51,4,0) -> Java | N88: =VLOOKUP(B88,'Patner Store'!A$1:F$51,5,0) -> Jakarta
A89: SO0088 | B89: PS0001 | C89: ST0005 | D89: 43934 | E89: Bali, East & West Nusa Tenggara | F89: CREDIT | G89: 600198050 | H89: The product is unavailable from the vendor or there has been a product replacement | I89: =VLOOKUP(C89,'Sales Team'!A$1:C$6,2,0) -> Sales Region Bali - Nusa Tenggara Team | J89: =VLOOKUP(C89,'Sales Team'!A$1:D$6,4,0) -> Corporate Negotiate/Patnership Contract | K89: =VLOOKUP(B89,'Patner Store'!A$1:F$51,2,0) -> Sport Nation | L89: =VLOOKUP(B89,'Patner Store'!A$1:F$51,3,0) -> Distributor | M89: =VLOOKUP(B89,'Patner Store'!A$1:F$51,4,0) -> Bali | N89: =VLOOKUP(B89,'Patner Store'!A$1:F$51,5,0) -> Bali
A90: SO0089 | B90: PS0046 | C90: ST0003 | D90: 43934 | E90: Sumatera & Kalimantan | F90: CREDIT | G90: 256372920 | I90: =VLOOKUP(C90,'Sales Team'!A$1:C$6,2,0) -> Sales Sumatera -Kalimantan Region Team | J90: =VLOOKUP(C90,'Sales Team'!A$1:D$6,4,0) -> OnlineMarketing/Corporate Negotiate/Patnership Contract | K90: =VLOOKUP(B90,'Patner Store'!A$1:F$51,2,0) -> Markas Olahraga | L90: =VLOOKUP(B90,'Patner Store'!A$1:F$51,3,0) -> Retail | M90: =VLOOKUP(B90,'Patner Store'!A$1:F$51,4,0) -> Kalimantan | N90: =VLOOKUP(B90,'Patner Store'!A$1:F$51,5,0) -> South Kalimantan
A91: SO0090 | B91: PS0029 | C91: ST0004 | D91: 43935 | E91: Sulawesi, Maluku, North Maluku | F91: CREDIT | G91: 359696134 | H91: The product is unavailable from the vendor or there has been a product replacement | I91: =VLOOKUP(C91,'Sales Team'!A$1:C$6,2,0) -> Sales Region Sulawesi - Maluku Team | J91: =VLOOKUP(C91,'Sales Team'!A$1:D$6,4,0) -> Corporate Negotiate/Patnership Contract | K91: =VLOOKUP(B91,'Patner Store'!A$1:F$51,2,0) -> Mama Sport | L91: =VLOOKUP(B91,'Patner Store'!A$1:F$51,3,0) -> Retail | M91: =VLOOKUP(B91,'Patner Store'!A$1:F$51,4,0) -> North Maluku | N91: =VLOOKUP(B91,'Patner Store'!A$1:F$51,5,0) -> North Maluku
A92: SO0091 | B92: PS0010 | C92: ST0001 | D92: 43936 | E92: Jakarta | F92: CASH | G92: 223064820 | I92: =VLOOKUP(C92,'Sales Team'!A$1:C$6,2,0) -> Online Sales Team | J92: =VLOOKUP(C92,'Sales Team'!A$1:D$6,4,0) -> OnlineMarketing | K92: =VLOOKUP(B92,'Patner Store'!A$1:F$51,2,0) -> WorldSport.com | L92: =VLOOKUP(B92,'Patner Store'!A$1:F$51,3,0) -> Retail | M92: =VLOOKUP(B92,'Patner Store'!A$1:F$51,4,0) -> Java | N92: =VLOOKUP(B92,'Patner Store'!A$1:F$51,5,0) -> Jakarta
A93: SO0092 | B93: PS0025 | C93: ST0003 | D93: 43936 | E93: Sumatera & Kalimantan | F93: CREDIT | G93: 244572270 | H93: The product is unavailable from the vendor or there has been a product replacement | I93: =VLOOKUP(C93,'Sales Team'!A$1:C$6,2,0) -> Sales Sumatera -Kalimantan Region Team | J93: =VLOOKUP(C93,'Sales Team'!A$1:D$6,4,0) -> OnlineMarketing/Corporate Negotiate/Patnership Contract | K93: =VLOOKUP(B93,'Patner Store'!A$1:F$51,2,0) -> Toko Olahraga Unggul | L93: =VLOOKUP(B93,'Patner Store'!A$1:F$51,3,0) -> Retail | M93: =VLOOKUP(B93,'Patner Store'!A$1:F$51,4,0) -> Kalimantan | N93: =VLOOKUP(B93,'Patner Store'!A$1:F$51,5,0) -> South Kalimantan
A94: SO0093 | B94: PS0032 | C94: ST0004 | D94: 43938 | E94: Sulawesi, Maluku, North Maluku | F94: CREDIT | G94: 320330080 | I94: =VLOOKUP(C94,'Sales Team'!A$1:C$6,2,0) -> Sales Region Sulawesi - Maluku Team | J94: =VLOOKUP(C94,'Sales Team'!A$1:D$6,4,0) -> Corporate Negotiate/Patnership Contract | K94: =VLOOKUP(B94,'Patner Store'!A$1:F$51,2,0) -> Toko Idola Olahraga | L94: =VLOOKUP(B94,'Patner Store'!A$1:F$51,3,0) -> Retail | M94: =VLOOKUP(B94,'Patner Store'!A$1:F$51,4,0) -> Sulawesi | N94: =VLOOKUP(B94,'Patner Store'!A$1:F$51,5,0) -> North Sulawesi
A95: SO0094 | B95: PS0015 | C95: ST0004 | D95: 43938 | E95: Sulawesi, Maluku, North Maluku | F95: CASH | G95: 117155640 | I95: =VLOOKUP(C95,'Sales Team'!A$1:C$6,2,0) -> Sales Region Sulawesi - Maluku Team | J95: =VLOOKUP(C95,'Sales Team'!A$1:D$6,4,0) -> Corporate Negotiate/Patnership Contract | K95: =VLOOKUP(B95,'Patner Store'!A$1:F$51,2,0) -> Toko Olahraga Satu | L95: =VLOOKUP(B95,'Patner Store'!A$1:F$51,3,0) -> Retail | M95: =VLOOKUP(B95,'Patner Store'!A$1:F$51,4,0) -> North Maluku | N95: =VLOOKUP(B95,'Patner Store'!A$1:F$51,5,0) -> North Maluku
A96: SO0095 | B96: PS0046 | C96: ST0003 | D96: 43938 | E96: Sumatera & Kalimantan | F96: CASH | G96: 72653090 | I96: =VLOOKUP(C96,'Sales Team'!A$1:C$6,2,0) -> Sales Sumatera -Kalimantan Region Team | J96: =VLOOKUP(C96,'Sales Team'!A$1:D$6,4,0) -> OnlineMarketing/Corporate Negotiate/Patnership Contract | K96: =VLOOKUP(B96,'Patner Store'!A$1:F$51,2,0) -> Markas Olahraga | L96: =VLOOKUP(B96,'Patner Store'!A$1:F$51,3,0) -> Retail | M96: =VLOOKUP(B96,'Patner Store'!A$1:F$51,4,0) -> Kalimantan | N96: =VLOOKUP(B96,'Patner Store'!A$1:F$51,5,0) -> South Kalimantan
A97: SO0096 | B97: PS0048 | C97: ST0003 | D97: 43938 | E97: Sumatera & Kalimantan | F97: CREDIT | G97: 297933696 | I97: =VLOOKUP(C97,'Sales Team'!A$1:C$6,2,0) -> Sales Sumatera -Kalimantan Region Team | J97: =VLOOKUP(C97,'Sales Team'!A$1:D$6,4,0) -> OnlineMarketing/Corporate Negotiate/Patnership Contract | K97: =VLOOKUP(B97,'Patner Store'!A$1:F$51,2,0) -> Toko Olahraga Mandiri | L97: =VLOOKUP(B97,'Patner Store'!A$1:F$51,3,0) -> Retail | M97: =VLOOKUP(B97,'Patner Store'!A$1:F$51,4,0) -> Kalimantan | N97: =VLOOKUP(B97,'Patner Store'!A$1:F$51,5,0) -> South Kalimantan
A98: SO0097 | B98: PS0007 | C98: ST0001 | D98: 43939 | E98: Jakarta | F98: CASH | G98: 58267980 | H98: The product is unavailable from the vendor or there has been a product replacement | I98: =VLOOKUP(C98,'Sales Team'!A$1:C$6,2,0) -> Online Sales Team | J98: =VLOOKUP(C98,'Sales Team'!A$1:D$6,4,0) -> OnlineMarketing | K98: =VLOOKUP(B98,'Patner Store'!A$1:F$51,2,0) -> Twinsport.com | L98: =VLOOKUP(B98,'Patner Store'!A$1:F$51,3,0) -> Retail | M98: =VLOOKUP(B98,'Patner Store'!A$1:F$51,4,0) -> Java | N98: =VLOOKUP(B98,'Patner Store'!A$1:F$51,5,0) -> Jakarta
A99: SO0098 | B99: PS0031 | C99: ST0002 | D99: 43941 | E99: Java | F99: CREDIT | G99: 318965530 | H99: The transaction agreement has undergone changes | I99: =VLOOKUP(C99,'Sales Team'!A$1:C$6,2,0) -> Sales Java Region Team | J99: =VLOOKUP(C99,'Sales Team'!A$1:D$6,4,0) -> OnlineMarketing/Corporate Negotiate/Patnership Contract | K99: =VLOOKUP(B99,'Patner Store'!A$1:F$51,2,0) -> Toko Hidup Sehat | L99: =VLOOKUP(B99,'Patner Store'!A$1:F$51,3,0) -> Retail | M99: =VLOOKUP(B99,'Patner Store'!A$1:F$51,4,0) -> Java | N99: =VLOOKUP(B99,'Patner Store'!A$1:F$51,5,0) -> East Java
A100: SO0099 | B100: PS0007 | C100: ST0001 | D100: 43943 | E100: Jakarta | F100: CASH | G100: 236758060 | I100: =VLOOKUP(C100,'Sales Team'!A$1:C$6,2,0) -> Online Sales Team | J100: =VLOOKUP(C100,'Sales Team'!A$1:D$6,4,0) -> OnlineMarketing | K100: =VLOOKUP(B100,'Patner Store'!A$1:F$51,2,0) -> Twinsport.com | L100: =VLOOKUP(B100,'Patner Store'!A$1:F$51,3,0) -> Retail | M100: =VLOOKUP(B100,'Patner Store'!A$1:F$51,4,0) -> Java | N100: =VLOOKUP(B100,'Patner Store'!A$1:F$51,5,0) -> Jakarta
...

Sheet Product & Category Analysis
A1: Category Performance Overview
A2: Row Labels | B2: Total Revenue by Category | C2: Quantity Orders | D2: Orders each category | N2: Row Labels | O2: Orders each category | S2: Row Labels | T2: Quantity Orders
A3: Basketball | B3: 5778248850 | C3: 14162 | D3: 159 | N3: Basketball | O3: 159 | S3: Basketball | T3: 14162
A4: Bicycle | B4: 109802799810 | C4: 31926 | D4: 358 | N4: Bicycle | O4: 358 | S4: Bicycle | T4: 31926
A5: Billiard | B5: 13496671580 | C5: 27343 | D5: 332 | N5: Billiard | O5: 332 | S5: Billiard | T5: 27343
A6: Fishing Equipment | B6: 3419283660 | C6: 29794 | D6: 335 | N6: Fishing Equipment | O6: 335 | S6: Fishing Equipment | T6: 29794
A7: Futsal | B7: 3066297420 | C7: 13481 | D7: 165 | N7: Futsal | O7: 165 | S7: Futsal | T7: 13481
A8: Golf | B8: 69033801500 | C8: 42771 | D8: 482 | N8: Golf | O8: 482 | S8: Golf | T8: 42771
A9: Gym & Fitness | B9: 84120889453 | C9: 91209 | D9: 1024 | N9: Gym & Fitness | O9: 1024 | S9: Gym & Fitness | T9: 91209
A10: Hiking & Camping | B10: 6003969090 | C10: 30888 | D10: 355 | N10: Hiking & Camping | O10: 355 | S10: Hiking & Camping | T10: 30888
A11: Outdoors Sport | B11: 2047939440 | C11: 16032 | D11: 182 | N11: Outdoors Sport | O11: 182 | S11: Outdoors Sport | T11: 16032
A12: Grand Total | B12: 296769900803 | C12: 297606 | D12: 3392 | N12: Grand Total | O12: 3392 | S12: Grand Total | T12: 297606
A15: Revenue Contribution %
A16: Category | B16: Revenue | C16: Contribution%
A17: Basketball | B17: 5778248850 | C17: =GETPIVOTDATA("Total Revenue by Category",$A$2,"Category","Basketball")/GETPIVOTDATA("Total Revenue by Category",$A$2) -> 0.019470468
A18: Bicycle | B18: 109802799810 | C18: =GETPIVOTDATA("Total Revenue by Category",$A$2,"Category","Bicycle")/GETPIVOTDATA("Total Revenue by Category",$A$2) -> 0.36999305
A19: Billiard | B19: 13496671580 | C19: =GETPIVOTDATA("Total Revenue by Category",$A$2,"Category","Billiard")/GETPIVOTDATA("Total Revenue by Category",$A$2) -> 0.045478573
A20: Fishing Equipment | B20: 3419283660 | C20: =GETPIVOTDATA("Total Revenue by Category",$A$2,"Category","Fishing Equipment")/GETPIVOTDATA("Total Revenue by Category",$A$2) -> 0.011521666
A21: Futsal | B21: 3066297420 | C21: =GETPIVOTDATA("Total Revenue by Category",$A$2,"Category","Futsal")/GETPIVOTDATA("Total Revenue by Category",$A$2) -> 0.010332239
A22: Golf | B22: 69033801500 | C22: =GETPIVOTDATA("Total Revenue by Category",$A$2,"Category","Golf")/GETPIVOTDATA("Total Revenue by Category",$A$2) -> 0.23261726
A23: Gym & Fitness | B23: 84120889453 | C23: =GETPIVOTDATA("Total Revenue by Category",$A$2,"Category","Gym & Fitness")/GETPIVOTDATA("Total Revenue by Category",$A$2) -> 0.28345492
A24: Hiking & Camping | B24: 6003969090 | C24: =GETPIVOTDATA("Total Revenue by Category",$A$2,"Category","Hiking & Camping")/GETPIVOTDATA("Total Revenue by Category",$A$2) -> 0.020231058
A25: Outdoors Sport | B25: 2047939440 | C25: =GETPIVOTDATA("Total Revenue by Category",$A$2,"Category","Outdoors Sport")/GETPIVOTDATA("Total Revenue by Category",$A$2) -> 0.0069007653
A38: Top Products within Categories
A39: Row Labels | B39: Sum of ItemTotal | C39: Row Labels | D39: Sum of ItemTotal
A40: Bicycle | B40: 109802799810 | C40: Mountain Bike | D40: 31610057430
A41: Road Bike | B41: 78192742380 | C41: Treadmill | D41: 31829133590
A42: Mountain Bike | B42: 31610057430 | C42: Bench Press | D42: 35684926500
A43: Gym & Fitness | B43: 82515697090 | C43: Stick Golf Bag | D43: 39988768000
A44: Bench Press | B44: 35684926500 | C44: Road Bike | D44: 78192742380
A45: Dumbell Set | B45: 7134274280 | C45: Grand Total | D45: 217305627900
A46: Heavy bag | B46: 4940433960
A47: Pull Up Bar | B47: 2926928760
A48: Treadmill | B48: 31829133590
A49: Golf | B49: 69033801500
A50: 1 set Golf Ball | B50: 2476555950
A51: Stick Golf Bag | B51: 39988768000
A52: Stick Golf Wedge | B52: 26568477550
A53: Billiard | B53: 13496671580
A54: Stick Billiard | B54: 10971071580
A55: Stick Billiard Bag | B55: 2525600000
A56: Hiking & Camping | B56: 6003969090
A57: Hiking Shoes | B57: 4312590750
... A68: Grand Total | B68: 295164708440
A71: Product Demand Analysis
A72: Row Labels | B72: Quantity Order
A73: 1 Set Basketball | B73: 14162
A74: 1 Set Fishing Equipment | B74: 14942
A75: 1 Set Futsalball | B75: 13481
A76: 1 set Golf Ball | B76: 13867
A77: Abs Roller | B77: 13891
A78: Bench Press | B78: 15822
A79: Dumbell Set | B79: 15754
A80: Fishing soft lure | B80: 14852
A81: Heavy bag | B81: 18096
A82: Hiking Shoes | B82: 15592
A83: Mountain Bike | B83: 15694
A84: Pull Up Bar | B84: 12964
... A93: Grand Total | B93: 297606
A115: Top 5 Product Trend Analysis & Forecast
A116: Sum of ItemTotal | B116: Column Labels
A117: Row Labels | B117: Bench Press | C117: Mountain Bike | D117: Road Bike | E117: Stick Golf Bag | F117: Treadmill | G117: Grand Total
A118: Jan | B118: 3095544500 | C118: 2896946360 | D118: 6628475330 | E118: 1890048000 | F118: 2322648800 | G118: 16833662990
A119: Feb | B119: 2870374000 | C119: 3626679420 | D119: 8302525260 | E119: 3072512000 | F119: 2868211270 | G119: 20740301950
A120: Mar | B120: 3884767500 | C120: 2837924180 | D120: 5917115480 | E120: 4007808000 | F120: 2226067190 | G120: 18873682350
A121: Apr | B121: 3287166000 | C121: 3008574240 | D121: 8541675250 | E121: 1607392000 | F121: 3529600300 | G121: 19974407790
A122: May | B122: 2719615500 | C122: 3360230370 | D122: 7815259270 | E122: 4180352000 | F122: 2475894680 | G122: 20551351820
A123: Jun | B123: 2678169500 | C123: 2481337740 | D123: 5564057690 | E123: 3820064000 | F123: 2608340720 | G123: 17151969650
A124: Jul | B124: 3398466000 | C124: 1555265110 | D124: 3400035050 | E124: 2684832000 | F124: 2280539320 | G124: 13319137480
A125: Aug | B125: 3813509000 | C125: 1821501850 | D125: 6914767360 | E125: 2850336000 | F125: 2729137830 | G125: 18129252040
A126: Sep | B126: 1209168500 | C126: 1975520960 | D126: 5718002390 | E126: 2983328000 | F126: 1471792600 | G126: 13357812450
A127: Oct | B127: 4420200000 | C127: 2525993610 | D127: 7375417270 | E127: 3054272000 | F127: 2756131740 | G127: 20132014620
A128: Nov | B128: 2602061500 | C128: 2783737950 | D128: 7285249660 | E128: 5270272000 | F128: 3114852510 | G128: 21056173620
A129: Dec | B129: 1705884500 | C129: 2736345640 | D129: 4730162370 | E129: 4567552000 | F129: 3445916630 | G129: 17185861140
A130: Grand Total | B130: 35684926500 | C130: 31610057430 | D130: 78192742380 | E130: 39988768000 | F130: 31829133590 | G130: 217305627900
A135: 2020 | B135: 12696309000
A136: 2021 | B136: 10706079500
A137: 2022 | B137: 12282538000
A143: Sum of ItemTotal | B143: Column Labels
A144: Row Labels | B144: Bench Press | C144: Mountain Bike | D144: Road Bike | E144: Stick Golf Bag | F144: Treadmill | G144: Grand Total
A145: 2020 | B145: 12696309000 | C145: 11772330010 | D145: 30736440910 | E145: 13953568000 | F145: 12211417830 | G145: 81370065750
A146: 2021 | B146: 10706079500 | C146: 9702071610 | D146: 23877612430 | E146: 13554688000 | F146: 10623212400 | G146: 68463663940
A147: 2022 | B147: 12282538000 | C147: 10135655810 | D147: 23578689040 | E147: 12480512000 | F147: 8994503360 | G147: 67471898210
A148: Grand Total | B148: 35684926500 | C148: 31610057430 | D148: 78192742380 | E148: 39988768000 | F148: 31829133590 | G148: 217305627900
A149: Realistic Forecast
A150: Year Period | B150: Bench Press | C150: Mountain Bike | D150: Road Bike | E150: Stick Golf Bag | F150: Treadmill
A151: 2020 | B151: 12696309000 | C151: 11772330010 | D151: 30736440910 | E151: 13953568000 | F151: 12211417830
A152: 2021 | B152: 10706079500 | C152: 9702071610 | D152: 23877612430 | E152: 13554688000 | F152: 10623212400
A153: 2022 | B153: 12282538000 | C153: 10135655810 | D153: 23578689040 | E153: 12480512000 | F153: 8994503360
A154: 2023 | B154: =_xlfn.FORECAST.ETS(A154,B151:B153,A151:A153,1) -> 1.1614838e+10 | C154: =_xlfn.FORECAST.ETS(A154,C151:C153,A151:A153,1) -> 8.9938235e+09 | D154: =_xlfn.FORECAST.ETS(A154,D151:D153,A151:A153,1) -> 1.9152277e+10 | E154: =_xlfn.FORECAST.ETS(A154,E151:E153,A151:A153,1) -> 1.1831232e+10 | F154: =_xlfn.FORECAST.ETS(A154,F151:F153,A151:A153,1) -> 7.3912792e+09
A155: 2024 | B155: =_xlfn.FORECAST.ETS(A155,B151:B154,A151:A154,1) -> 1.1378212e+10 | C155: =_xlfn.FORECAST.ETS(A155,C151:C154,A151:A154,1) -> 8.154608e+09 | D155: =_xlfn.FORECAST.ETS(A155,D151:D154,A151:A154,1) -> 1.5518701e+10 | E155: =_xlfn.FORECAST.ETS(A155,E151:E154,A151:A154,1) -> 1.1100335e+10 | F155: =_xlfn.FORECAST.ETS(A155,F151:F154,A151:A154,1) -> 5.7831597e+09
A156: 2025 | B156: =_xlfn.FORECAST.ETS(A156,B151:B155,A151:A155,1) -> 1.1022024e+10 | C156: =_xlfn.FORECAST.ETS(A156,C151:C155,A151:A155,1) -> 7.2314598e+09 | D156: =_xlfn.FORECAST.ETS(A156,D151:D155,A151:A155,1) -> 1.1665227e+10 | E156: =_xlfn.FORECAST.ETS(A156,E151:E155,A151:A155,1) -> 1.0392075e+10 | F156: =_xlfn.FORECAST.ETS(A156,F151:F155,A151:A155,1) -> 4.1763979e+09
A158: Optimistic Forecast( Increase with growth Yearly Sales 2%)
A159: Year Period | B159: Bench Press | C159: Mountain Bike | D159: Road Bike | E159: Stick Golf Bag | F159: Treadmill
A160: 2020 | B160: 12696309000 | C160: 11772330010 | D160: 30736440910 | E160: 13953568000 | F160: 12211417830
A161: 2021 | B161: 10706079500 | C161: 9702071610 | D161: 23877612430 | E161: 13554688000 | F161: 10623212400
A162: 2022 | B162: 12282538000 | C162: 10135655810 | D162: 23578689040 | E162: 12480512000 | F162: 8994503360
A163: 2023 | B163: =B162*(1+0.02) -> 12528188760 | C163: =C162*(1+0.02) -> 1.0338369e+10 | D163: =D162*(1+0.02) -> 2.4050263e+10 | E163: =E162*(1+0.02) -> 12730122240 | F163: =F162*(1+0.02) -> 9.1743934e+09
A164: 2024 | B164: =B163*(1+0.02) -> 1.2778753e+10 | C164: =C163*(1+0.02) -> 1.0545136e+10 | D164: =D163*(1+0.02) -> 2.4531268e+10 | E164: =E163*(1+0.02) -> 1.2984725e+10 | F164: =F163*(1+0.02) -> 9.3578813e+09
A165: 2025 | B165: =B164*(1+0.02) -> 1.3034328e+10 | C165: =C164*(1+0.02) -> 1.0756039e+10 | D165: =D164*(1+0.02) -> 2.5021893e+10 | E165: =E164*(1+0.02) -> 1.3244419e+10 | F165: =F164*(1+0.02) -> 9.5450389e+09
...

Sheet Order Item
A1: SalesOrderID | B1: OrderDate | C1: ProductID | D1: QuantityOrder | E1: ItemTotal | F1: OrderItemID | G1: ProductName | H1: Category | I1: ProductName | J1: QuantityOrder | K1: SalesTeamName | L1: Prospect per Sales Team | M1: Patner Type
A2: SO0001 | B2: =VLOOKUP(A2,'Sales Order'!A$1:D$1029,4,0) -> 43832 | C2: PD0002 | D2: 99 | E2: 1841400 | F2: SO0001-PD0002 | G2: =VLOOKUP(C2,Product!A$1:D$21,3,0) -> Fishing soft lure | H2: =VLOOKUP(C2,Product!A$1:D$21,4,0) -> Fishing Equipment | I2: Fishing soft lure | J2: 99 | K2: =VLOOKUP(A2,'Sales Order'!A$2:I$1029,9,0) -> Sales Sumatera -Kalimantan Region Team | M2: =VLOOKUP(A2,'Sales Order'!A$1:L$1029,12,0) -> Retail
A3: SO0001 | B3: =VLOOKUP(A3,'Sales Order'!A$1:D$1029,4,0) -> 43832 | C3: PD0015 | D3: 89 | E3: 9192276 | F3: SO0001-PD0015 | G3: =VLOOKUP(C3,Product!A$1:D$21,3,0) -> Abs Roller | H3: =VLOOKUP(C3,Product!A$1:D$21,4,0) -> Gym & Fitness | I3: Abs Roller | J3: 89 | K3: =VLOOKUP(A3,'Sales Order'!A$2:I$1029,9,0) -> Sales Sumatera -Kalimantan Region Team | M3: =VLOOKUP(A3,'Sales Order'!A$1:L$1029,12,0) -> Retail
A4: SO0001 | B4: =VLOOKUP(A4,'Sales Order'!A$1:D$1029,4,0) -> 43832 | C4: PD0011 | D4: 45 | E4: 93416400 | F4: SO0001-PD0011 | G4: =VLOOKUP(C4,Product!A$1:D$21,3,0) -> Mountain Bike | H4: =VLOOKUP(C4,Product!A$1:D$21,4,0) -> Bicycle | I4: Mountain Bike | J4: 45 | K4: =VLOOKUP(A4,'Sales Order'!A$2:I$1029,9,0) -> Sales Sumatera -Kalimantan Region Team | M4: =VLOOKUP(A4,'Sales Order'!A$1:L$1029,12,0) -> Retail
A5: SO0001 | B5: =VLOOKUP(A5,'Sales Order'!A$1:D$1029,4,0) -> 43832 | C5: PD0008 | D5: 72 | E5: 10191600 | F5: SO0001-PD0008 | G5: =VLOOKUP(C5,Product!A$1:D$21,3,0) -> Sunglasses | H5: =VLOOKUP(C5,Product!A$1:D$21,4,0) -> Outdoors Sport | I5: Sunglasses | J5: 72 | K5: =VLOOKUP(A5,'Sales Order'!A$2:I$1029,9,0) -> Sales Sumatera -Kalimantan Region Team | M5: =VLOOKUP(A5,'Sales Order'!A$1:L$1029,12,0) -> Retail
A6: SO0002 | B6: =VLOOKUP(A6,'Sales Order'!A$1:D$1029,4,0) -> 43832 | C6: PD0014 | D6: 77 | E6: 17063970 | F6: SO0002-PD0014 | G6: =VLOOKUP(C6,Product!A$1:D$21,3,0) -> 1 Set Futsalball | H6: =VLOOKUP(C6,Product!A$1:D$21,4,0) -> Futsal | I6: 1 Set Futsalball | J6: 77 | K6: =VLOOKUP(A6,'Sales Order'!A$2:I$1029,9,0) -> Sales Sumatera -Kalimantan Region Team | M6: =VLOOKUP(A6,'Sales Order'!A$1:L$1029,12,0) -> Retail
A7: SO0002 | B7: =VLOOKUP(A7,'Sales Order'!A$1:D$1029,4,0) -> 43832 | C7: PD0010 | D7: 92 | E7: 27807000 | F7: SO0002-PD0010 | G7: =VLOOKUP(C7,Product!A$1:D$21,3,0) -> Hiking Shoes | H7: =VLOOKUP(C7,Product!A$1:D$21,4,0) -> Hiking & Camping | I7: Hiking Shoes | J7: 92 | K7: =VLOOKUP(A7,'Sales Order'!A$2:I$1029,9,0) -> Sales Sumatera -Kalimantan Region Team | M7: =VLOOKUP(A7,'Sales Order'!A$1:L$1029,12,0) -> Retail
A8: SO0003 | B8: =VLOOKUP(A8,'Sales Order'!A$1:D$1029,4,0) -> 43833 | C8: PD0011 | D8: 142 | E8: 291430860 | F8: SO0003-PD0011 | G8: =VLOOKUP(C8,Product!A$1:D$21,3,0) -> Mountain Bike | H8: =VLOOKUP(C8,Product!A$1:D$21,4,0) -> Bicycle | I8: Mountain Bike | J8: 142 | K8: =VLOOKUP(A8,'Sales Order'!A$2:I$1029,9,0) -> Online Sales Team | M8: =VLOOKUP(A8,'Sales Order'!A$1:L$1029,12,0) -> Retail
A9: SO0003 | B9: =VLOOKUP(A9,'Sales Order'!A$1:D$1029,4,0) -> 43833 | C9: PD0018 | D9: 125 | E9: 51870000 | F9: SO0003-PD0018 | G9: =VLOOKUP(C9,Product!A$1:D$21,3,0) -> Dumbell Set | H9: =VLOOKUP(C9,Product!A$1:D$21,4,0) -> Gym & Fitness | I9: Dumbell Set | J9: 125 | K9: =VLOOKUP(A9,'Sales Order'!A$2:I$1029,9,0) -> Online Sales Team | M9: =VLOOKUP(A9,'Sales Order'!A$1:L$1029,12,0) -> Retail
A10: SO0003 | B10: =VLOOKUP(A10,'Sales Order'!A$1:D$1029,4,0) -> 43833 | C10: PD0010 | D10: 150 | E10: 44850000 | F10: SO0003-PD0010 | G10: =VLOOKUP(C10,Product!A$1:D$21,3,0) -> Hiking Shoes | H10: =VLOOKUP(C10,Product!A$1:D$21,4,0) -> Hiking & Camping | I10: Hiking Shoes | J10: 150 | K10: =VLOOKUP(A10,'Sales Order'!A$2:I$1029,9,0) -> Online Sales Team | M10: =VLOOKUP(A10,'Sales Order'!A$1:L$1029,12,0) -> Retail
A11: SO0003 | B11: =VLOOKUP(A11,'Sales Order'!A$1:D$1029,4,0) -> 43833 | C11: PD0008 | D11: 94 | E11: 12885520 | F11: SO0003-PD0008 | G11: =VLOOKUP(C11,Product!A$1:D$21,3,0) -> Sunglasses | H11: =VLOOKUP(C11,Product!A$1:D$21,4,0) -> Outdoors Sport | I11: Sunglasses | J11: 94 | K11: =VLOOKUP(A11,'Sales Order'!A$2:I$1029,9,0) -> Online Sales Team | M11: =VLOOKUP(A11,'Sales Order'!A$1:L$1029,12,0) -> Retail
A12: SO0003 | B12: =VLOOKUP(A12,'Sales Order'!A$1:D$1029,4,0) -> 43833 | C12: PD0012 | D12: 128 | E12: 671266560 | F12: SO0003-PD0012 | G12: =VLOOKUP(C12,Product!A$1:D$21,3,0) -> Road Bike | H12: =VLOOKUP(C12,Product!A$1:D$21,4,0) -> Bicycle | I12: Road Bike | J12: 128 | K12: =VLOOKUP(A12,'Sales Order'!A$2:I$1029,9,0) -> Online Sales Team | M12: =VLOOKUP(A12,'Sales Order'!A$1:L$1029,12,0) -> Retail
A13: SO0003 | B13: =VLOOKUP(A13,'Sales Order'!A$1:D$1029,4,0) -> 43833 | C13: PD0020 | D13: 101 | E13: 29503110 | F13: SO0003-PD0020 | G13: =VLOOKUP(C13,Product!A$1:D$21,3,0) -> Heavy bag | H13: =VLOOKUP(C13,Product!A$1:D$21,4,0) -> Gym & Fitness | I13: Heavy bag | J13: 101 | K13: =VLOOKUP(A13,'Sales Order'!A$2:I$1029,9,0) -> Online Sales Team | M13: =VLOOKUP(A13,'Sales Order'!A$1:L$1029,12,0) -> Retail
... A3393: SO1027 | B3393: =VLOOKUP(A3393,'Sales Order'!A$1:D$1029,4,0) -> 44914 | C3393: PD0007 | D3393: 121 | E3393: 367840000 | F3393: SO1027-PD0007 | G3393: =VLOOKUP(C3393,Product!A$1:D$21,3,0) -> Stick Golf Bag | H3393: =VLOOKUP(C3393,Product!A$1:D$21,4,0) -> Golf | I3393: Stick Golf Bag | J3393: 121 | K3393: =VLOOKUP(A3393,'Sales Order'!A$2:I$1029,9,0) -> Sales Region Bali - Nusa Tenggara Team | M3393: =VLOOKUP(A3393,'Sales Order'!A$1:L$1029,12,0) -> Retail
M3394: =VLOOKUP(A3394,'Sales Order'!A$1:L$1029,12,0) -> #N/A
M3395: =VLOOKUP(A3395,'Sales Order'!A$1:L$1029,12,0) -> #N/A
M3396: =VLOOKUP(A3396,'Sales Order'!A$1:L$1029,12,0) -> #N/A
M3397: =VLOOKUP(A3397,'Sales Order'!A$1:L$1029,12,0) -> #N/A
M3398: =VLOOKUP(A3398,'Sales Order'!A$1:L$1029,12,0) -> #N/A
M3399: =VLOOKUP(A3399,'Sales Order'!A$1:L$1029,12,0) -> #N/A
M3400: =VLOOKUP(A3400,'Sales Order'!A$1:L$1029,12,0) -> #N/A
M3401: =VLOOKUP(A3401,'Sales Order'!A$1:L$1029,12,0) -> #N/A
M3402: =VLOOKUP(A3402,'Sales Order'!A$1:L$1029,12,0) -> #N/A
M3403: =VLOOKUP(A3403,'Sales Order'!A$1:L$1029,12,0) -> #N/A
M3404: =VLOOKUP(A3404,'Sales Order'!A$1:L$1029,12,0) -> #N/A
M3405: =VLOOKUP(A3405,'Sales Order'!A$1:L$1029,12,0) -> #N/A
... M4000: =VLOOKUP(A4000,'Sales Order'!A$1:L$1029,12,0) -> #N/A

Sheet Vendor
A1: VendorID | B1: VendorName | C1: Address | D1: City | E1: Province | F1: Email | G1: Phone
A2: VD0001 | B2: PT.Aneka Olahraga | C2: Jl. Tanjong Priok No.23 | D2: North Jakarta | E2: Jakarta | F2: Anekasport@net.id | G2: +62 87 1651 6391
A3: VD0002 | B3: Sportspirit Inc | C3: Ubi Ave Street No.3 | D3: Singapore City | E3: Singapore | F3: sportspirit.co.id | G3: +65 8249 7112
A4: VD0003 | B4: PT.Fortune Sport | C4: Jl. Gajah Mada No.78 | D4: Central Jakarta | E4: Jakarta | F4: fortunesport.com | G4: +62 82 2497 3691

Sheet Product
A1: ProductID | B1: VendorID | C1: ProductName | D1: Category | E1: UnitSalesPrice | F1: UnitBuyPrice | G1: Quantity | H1: UOM | I1: DiscountProduct | J1: Product Description
A2: PD0001 | B2: VD0002 | C2: 1 Set Fishing Equipment | D2: Fishing Equipment | E2: 249000 | F2: 180000 | G2: 12547 | H2: Set | I2: 0.3 | J2: Joran, Reel, Tas, Senar, Mata kail, Stoper, Starlet
A3: PD0002 | B3: VD0002 | C3: Fishing soft lure | D3: Fishing Equipment | E3: 20000 | F3: 14000 | G3: 14769 | H3: Unit | I3: 0.1
A4: PD0003 | B4: VD0003 | C4: Stick Billiard | D4: Billiard | E4: 931000 | F4: 785000 | G4: 5654 | H4: Unit | I4: 0.2 | J4: Tip Size : 11.75mm, dan Length : 148 cm
A5: PD0004 | B5: VD0003 | C5: Stick Billiard Bag | D5: Billiard | E5: 220000 | F5: 175000 | G5: 3275 | H5: Unit | I5: 0.25
A6: PD0005 | B6: VD0001 | C6: Stick Golf Wedge | D6: Golf | E6: 2195000 | F6: 1785000 | G6: 3431 | H6: Unit | I6: 0.2 | J6: Degree : 52, 56, 60, 64
A7: PD0006 | B7: VD0001 | C7: 1 set Golf Ball | D7: Golf | E7: 209000 | F7: 195000 | G7: 8123 | H7: Set | I7: 0.2 | J7: 12 bola golf
A8: PD0007 | B8: VD0001 | C8: Stick Golf Bag | D8: Golf | E8: 3200000 | F8: 2800000 | G8: 2288 | H8: Unit | I8: 0.2
A9: PD0008 | B9: VD0002 | C9: Sunglasses | D9: Outdoors Sport | E9: 149000 | F9: 118000 | G9: 11023 | H9: Unit | I9: 0.15
A10: PD0009 | B10: VD0002 | C10: Tracking Pole | D10: Hiking & Camping | E10: 129000 | F10: 105000 | G10: 1418 | H10: Unit | I10: 0.15 | J10: Ukuran untuk Anak - anak : 100 cm, dan Dewasa : 125 com
A11: PD0010 | B11: VD0002 | C11: Hiking Shoes | D11: Hiking & Camping | E11: 325000 | F11: 250000 | G11: 3361 | H11: Unit | I11: 0.25 | J11: Size tersedia : 40/25.5cm - 44/29.5cm
A12: PD0011 | B12: VD0003 | C12: Mountain Bike | D12: Bicycle | E12: 2359000 | F12: 2000000 | G12: 2393 | H12: Unit | I12: 0.2 | J12: Warna : Hitam Merah, Grey Orange, Teal, Hitam biru
A13: PD0012 | B13: VD0003 | C13: Road Bike | D13: Bicycle | E13: 5639000 | F13: 4800000 | G13: 2710 | H13: Unit | I13: 0.2 | J13: Tipe Sepeda balap Performance dan All - around
A14: PD0013 | B14: VD0001 | C14: 1 Set Basketball | D14: Basketball | E14: 479000 | F14: 395000 | G14: 17561 | H14: Set | I14: 0.3 | J14: 5 Bola Basket
A15: PD0014 | B15: VD0001 | C15: 1 Set Futsalball | D15: Futsal | E15: 267000 | F15: 225000 | G15: 17743 | H15: Set | I15: 0.3 | J15: 5 Bola Futsal
A16: PD0015 | B16: VD0002 | C16: Abs Roller | D16: Gym & Fitness | E16: 135900 | F16: 95000 | G16: 3479 | H16: Unit | I16: 0.25
A17: PD0016 | B17: VD0002 | C17: Pull Up Bar | D17: Gym & Fitness | E17: 267000 | F17: 210000 | G17: 5101 | H17: Unit | I17: 0.25 | J17: Size : 80-130 cm
A18: PD0017 | B18: VD0002 | C18: Bench Press | D18: Gym & Fitness | E18: 2650000 | F18: 2200000 | G18: 2546 | H18: Unit | I18: 0.1 | J18: Dimensi : 142 x 110 x 108 cm
A19: PD0018 | B19: VD0002 | C19: Dumbell Set | D19: Gym & Fitness | E19: 532000 | F19: 485000 | G19: 11648 | H19: Unit | I19: 0.1 | J19: 2x 35cm (14") Stick Chrome, 1 pcs 152cm Stick, 6pcs Collar pengunci, 4pcs 1 kg plates, 2pcs 2 kg, 2pcs kg
A20: PD0019 | B20: VD0001 | C20: Treadmill | D20: Gym & Fitness | E20: 2549000 | F20: 2250000 | G20: 3106 | H20: Unit | I20: 0.25
A21: PD0020 | B21: VD0001 | C21: Heavy bag | D21: Gym & Fitness | E21: 321000 | F21: 275000 | G21: 3151 | H21: Unit | I21: 0.25

Sheet Patner Store
A1: PatnerStoreID | B1: PatnerStoreName | C1: PatnerType | D1: Region | E1: Province | F1: PatnerContactPhone
A2: PS0001 | B2: Sport Nation | C2: Distributor | D2: Bali | E2: Bali | F2: +62 837 3881 3393
A3: PS0002 | B3: TokoSport | C3: Retail | D3: Java | E3: East Java | F3: +62 843 0014 8341
A4: PS0003 | B4: Toko Gelora Sport | C4: Retail | D4: Kalimantan | E4: Central Kalimantan | F4: +62 856 3951 0850
A5: PS0004 | B5: Sport Line Indonesia | C5: Retail | D5: Java | E5: Jakarta | F5: +62 844 6558 9313
A6: PS0005 | B6: Sportworld | C6: Distributor | D6: Sulawesi | E6: South Sulawesi | F6: +62 834 8087 5084
A7: PS0006 | B7: Arena Sport Shop | C7: Retail | D7: Kalimantan | E7: Central Kalimantan | F7: +62 897 3528 4125
A8: PS0007 | B8: Twinsport.com | C8: Retail | D8: Java | E8: Jakarta | F8: +62 809 1899 6494
A9: PS0008 | B9: Amanah Sport | C9: Retail | D9: Sulawesi | E9: North Sulawesi | F9: +62 854 5164 5861
A10: PS0009 | B10: Olahraga Mall | C10: Distributor | D10: Sumatera | E10: South Sumatera | F10: +62 888 2771 3218
A11: PS0010 | B11: WorldSport.com | C11: Retail | D11: Java | E11: Jakarta | F11: +62 824 4696 3312
A12: PS0011 | B12: Atlethic Shop | C12: Retail | D12: Java | E12: East Java | F12: +62 878 0243 7778
... A51: PS0050 | B51: Toko Peralatan Olahraga | C51: Retail | D51: Maluku | E51: Maluku | F51: +62 888 9236 8417

Sheet PartnerStore Behaviour Analysis
A1: Partner Store Contribution Analysis
A2: Row Labels | B2: Sum of TotalOrderTransaction
A3: Toko Olahraga NTT | B3: 7028787634
A4: Mama Sport | B4: 7663872530
A5: Sport Line Indonesia | B5: 8044750889
A6: Destination Sport Store | B6: 8056757607
A7: Toko SportNesia | B7: 8236567341
A8: KakaSport | B8: 8237816158
A9: Salam Olahraga | B9: 8270107450
A10: SportMania Store | B10: 8349863320
A11: Sport Hub Medan | B11: 8466441644
A12: Toko Hidup Sehat | B12: 9429903378
A13: Grand Total | B13: 81784867951
A21: Partner Store | B21: Sum of TotalOrderTransaction | C21: Revenue Contribution(%)
A22: Active Sport | B22: 3900827045 | C22: =B22/B$72 -> 0.013144281
A23: Adi Shop | B23: 4293251970 | C23: =B23/B$72 -> 0.014466602
A24: Amanah Sport | B24: 3889569785 | C24: =B24/B$72 -> 0.013106349
A25: Arena Sport Shop | B25: 5580899608 | C25: =B25/B$72 -> 0.018805477
A26: Atlethic Shop | B26: 4952467699 | C26: =B26/B$72 -> 0.016687904
A27: Barokah Olahraga Shop | B27: 6026424376 | C27: =B27/B$72 -> 0.020306724
A28: Bebasport.com | B28: 3639962330 | C28: =B28/B$72 -> 0.012265268
A29: Destination Sport Store | B29: 8056757607 | C29: =B29/B$72 -> 0.027148163
A30: GilaSport.id | B30: 6012482646 | C30: =B30/B$72 -> 0.020259745
A31: Gudang Sport Center | B31: 4084865339 | C31: =B31/B$72 -> 0.013764419
A32: KakaSport | B32: 8237816158 | C32: =B32/B$72 -> 0.02775826
A33: Kartika Sport Center | B33: 5661787469 | C33: =B33/B$72 -> 0.019078038
... A71: WorldSport.com | B71: 5834510219 | C71: =B71/B$72 -> 0.019660047
A72: Grand Total | B72: 296769900803
A84: Partner Store Loyalty / Repeat Transaction
A85: Top Repeat Customers
A86: Row Labels | B86: Count of SalesOrder
A87: Atlethic Shop | B87: 24
A88: Toko Joko Sport | B88: 24
A89: Toko Hidup Sehat | B89: 24
A90: Olahraga Gemilang | B90: 25
A91: SportMania Store | B91: 25
A92: Surya Sport | B92: 25
A93: Sport Kita Store | B93: 25
A94: Barokah Olahraga Shop | B94: 26
A95: Destination Sport Store | B95: 27
A96: Mama Sport | B96: 27
A97: Grand Total | B97: 252
A106: Revenue vs Repeat Transactions
A107: Row Labels | B107: Sum of TotalOrderTransaction | C107: Count of SalesOrder
A108: Active Sport | B108: 3900827045 | C108: 20
A109: Adi Shop | B109: 4293251970 | C109: 18
A110: Amanah Sport | B110: 3889569785 | C110: 17
A111: Arena Sport Shop | B111: 5580899608 | C111: 18
A112: Atlethic Shop | B112: 4952467699 | C112: 24
A113: Barokah Olahraga Shop | B113: 6026424376 | C113: 26
A114: Bebasport.com | B114: 3639962330 | C114: 20
A115: Destination Sport Store | B115: 8056757607 | C115: 27
A116: GilaSport.id | B116: 6012482646 | C116: 20
A117: Gudang Sport Center | B117: 4084865339 | C117: 18
A118: KakaSport | B118: 8237816158 | C118: 22
A119: Kartika Sport Center | B119: 5661787469 | C119: 22
... A157: WorldSport.com | B157: 5834510219 | C157: 20
A159: Partner Type Analysis
A160: Revenue Contribution by Partner Type
A161: Row Labels | B161: Sum of TotalOrderTransaction
A162: Distributor | B162: 27338152378
A163: Retail | B163: 269431748425
A164: Grand Total | B164: 296769900803
A177: Orders by Partner Type
A178: Row Labels | B178: Count of SalesOrder
A179: Distributor | B179: 87
A180: Retail | B180: 941
A181: Grand Total | B181: 1028
A193: Quantity by Partner Type
A194: Row Labels | B194: Sum of QuantityOrder
A195: Distributor | B195: 26008
A196: Retail | B196: 271598
A197: Grand Total | B197: 297606
A208: High and Low Partner Stores
A209: High Patner Stores
A210: Row Labels | B210: Sum of TotalOrderTransaction
A211: Toko Olahraga NTT | B211: 7028787634
A212: Mama Sport | B212: 7663872530
A213: Sport Line Indonesia | B213: 8044750889
A214: Destination Sport Store | B214: 8056757607
A215: Toko SportNesia | B215: 8236567341
A216: KakaSport | B216: 8237816158
A217: Salam Olahraga | B217: 8270107450
A218: SportMania Store | B218: 8349863320
A219: Sport Hub Medan | B219: 8466441644
A220: Toko Hidup Sehat | B220: 9429903378
A221: Grand Total | B221: 81784867951
A224: Low Patner Stores
A225: Row Labels | B225: Sum of TotalOrderTransaction
A226: SportXpress | B226: 4533766155
A227: Toko Olahraga NTB | B227: 4475866728
A228: Toko Olahraga Mandiri | B228: 4458097283
A229: Adi Shop | B229: 4293251970
A230: Gudang Sport Center | B230: 4084865339
A231: Active Sport | B231: 3900827045
A232: Amanah Sport | B232: 3889569785
A233: Bebasport.com | B233: 3639962330
A234: Sportworld | B234: 3514691088
A235: Power Play | B235: 3412884933
A236: Grand Total | B236: 40203782656
...

Sheet Region & Sales Team Analysis
A1: Regional Performance Overview
A2: Row Labels | B2: Sum of TotalOrderTransaction | C2: Revenue Contribution
A3: Bali, East & West Nusa Tenggara | B3: 37219216848 | C3: =GETPIVOTDATA("TotalOrderTransaction",$A$2,"Region Sales Team","Bali, East & West Nusa Tenggara")/GETPIVOTDATA("TotalOrderTransaction",$A$2) -> 0.12541439
A4: Jakarta | B4: 52171345412 | C4: =GETPIVOTDATA("TotalOrderTransaction",$A$2,"Region Sales Team","Jakarta")/GETPIVOTDATA("TotalOrderTransaction",$A$2) -> 0.17579729
A5: Java | B5: 35941934604 | C5: =GETPIVOTDATA("TotalOrderTransaction",$A$2,"Region Sales Team","Java")/GETPIVOTDATA("TotalOrderTransaction",$A$2) -> 0.12111044
A6: Sulawesi, Maluku, North Maluku | B6: 103200235883 | C6: =GETPIVOTDATA("TotalOrderTransaction",$A$2,"Region Sales Team","Sulawesi, Maluku, North Maluku")/GETPIVOTDATA("TotalOrderTransaction",$A$2) -> 0.34774496
A7: Sumatera & Kalimantan | B7: 68237168056 | C7: =GETPIVOTDATA("TotalOrderTransaction",$A$2,"Region Sales Team","Sumatera & Kalimantan")/GETPIVOTDATA("TotalOrderTransaction",$A$2) -> 0.22993291
A8: Grand Total | B8: 296769900803
A28: Sales Team Performance & Trend Analysis
A29: Row Labels | B29: Sum of TotalOrderTransaction | E29: Row Labels | F29: Sum of QuantityOrder
A30: Online Sales Team | B30: 52171345412 | E30: Online Sales Team | F30: 55043
A31: Sales Java Region Team | B31: 35941934604 | E31: Sales Java Region Team | F31: 37129
A32: Sales Region Bali - Nusa Tenggara Team | B32: 37219216848 | E32: Sales Region Bali - Nusa Tenggara Team | F32: 35523
A33: Sales Region Sulawesi - Maluku Team | B33: 103200235883 | E33: Sales Region Sulawesi - Maluku Team | F33: 100928
A34: Sales Sumatera -Kalimantan Region Team | B34: 68237168056 | E34: Sales Sumatera -Kalimantan Region Team | F34: 68983
A35: Grand Total | B35: 296769900803 | E35: Grand Total | F35: 297606
A56: Multi-line Chart → Monthly Revenue Trend by Sales Team
A57: Sum of TotalOrderTransaction | B57: Column Labels
A58: Row Labels | B58: Online Sales Team | C58: Sales Java Region Team | D58: Sales Region Bali - Nusa Tenggara Team | E58: Sales Region Sulawesi - Maluku Team | F58: Sales Sumatera -Kalimantan Region Team | G58: Grand Total
A59: 2020 | B59: 24000030054 | C59: 12750281970 | D59: 15017127216 | E59: 37211661794 | F59: 22091747126 | G59: 111070848160
A60: 2021 | B60: 16306957968 | C60: 9530182325 | D60: 9559577587 | E60: 34397944631 | F60: 22165731721 | G60: 91960394232
A61: 2022 | B61: 11864357390 | C61: 13661470309 | D61: 12642512045 | E61: 31590629458 | F61: 23979689209 | G61: 93738658411
A62: Grand Total | B62: 52171345412 | C62: 35941934604 | D62: 37219216848 | E62: 103200235883 | F62: 68237168056 | G62: 296769900803
A83: Sales Promotion Method Analysis
A84: Revenue Contribution by Promotion Method
A85: Row Labels | B85: Sum of TotalOrderTransaction
A86: Corporate Negotiate/Patnership Contract | B86: 140419452731
A87: OnlineMarketing | B87: 52171345412
A88: OnlineMarketing/Corporate Negotiate/Patnership Contract | B88: 104179102660
A89: Grand Total | B89: 296769900803
A103: Prospect Contribution by Promotion Method
A104: Row Labels | B104: Sum of TotalProspect
A105: Corporate Negotiate/Patnership Contract | B105: 22
A106: OnlineMarketing | B106: 10
A107: OnlineMarketing/Corporate Negotiate/Patnership Contract | B107: 18
A108: Grand Total | B108: 50
A124: Conversion / Efficiency Analysis
A125: Row Labels | B125: Sum of TotalProspect | C125: Revenue Per Prospect
A126: Corporate Negotiate/Patnership Contract | B126: 22 | C126: 6.3827024e+09
A127: OnlineMarketing | B127: 10 | C127: 5.2171345e+09
A128: OnlineMarketing/Corporate Negotiate/Patnership Contract | B128: 18 | C128: 5.7877279e+09
A129: Grand Total | B129: 50 | C129: 5.935398e+09
A140: High & Low Performing Sales Teams
A141: High Performing Sales Teams
A142: Row Labels | B142: Sum of TotalOrderTransaction
A143: Sales Region Sulawesi - Maluku Team | B143: 103200235883
A144: Sales Sumatera -Kalimantan Region Team | B144: 68237168056
A145: Online Sales Team | B145: 52171345412
A146: Grand Total | B146: 223608749351
A158: Low Performing Sales Teams
A159: Row Labels | B159: Sum of TotalOrderTransaction
A160: Sales Region Bali - Nusa Tenggara Team | B160: 37219216848
A161: Sales Java Region Team | B161: 35941934604
A162: Grand Total | B162: 73161151452
A175: Sales Team Efficiency Analysis
A176: Row Labels | B176: Sum of QuantityOrder | C176: Sum of Revenue | D176: Total Prospect | E176: Revenue per Prospect | F176: Orders Per Prospect
A177: Online Sales Team | B177: 55043 | C177: 52171345412 | D177: 10 | E177: =C177/D177 -> 5.2171345e+09 | F177: =B177/D177 -> 5504.3
A178: Sales Java Region Team | B178: 37129 | C178: 35941934604 | D178: 6 | E178: =C178/D178 -> 5990322434 | F178: =B178/D178 -> 6188.1667
A179: Sales Region Bali - Nusa Tenggara Team | B179: 35523 | C179: 37219216848 | D179: 12 | E179: =C179/D179 -> 3101601404 | F179: =B179/D179 -> 2960.25
A180: Sales Region Sulawesi - Maluku Team | B180: 100928 | C180: 103200235883 | D180: 16 | E180: =C180/D180 -> 6.4500147e+09 | F180: =B180/D180 -> 6308
A181: Sales Sumatera -Kalimantan Region Team | B181: 68983 | C181: 68237168056 | D181: 6 | E181: =C181/D181 -> 1.1372861e+10 | F181: =B181/D181 -> 11497.167
A182: Grand Total | B182: 297606 | C182: 296769900803 | D182: 50 | E182: =C182/D182 -> 5.935398e+09 | F182: =B182/D182 -> 5952.12

Sheet Sales Team
A1: SalesTeamID | B1: SalesTeamName | C1: SalesTeamRegion | D1: SalesPromotionMethods | E1: TotalProspect
A2: ST0001 | B2: Online Sales Team | C2: Jakarta | D2: OnlineMarketing | E2: 10
A3: ST0002 | B3: Sales Java Region Team | C3: Java | D3: OnlineMarketing/Corporate Negotiate/Patnership Contract | E3: 6
A4: ST0003 | B4: Sales Sumatera -Kalimantan Region Team | C4: Sumatera & Kalimantan | D4: OnlineMarketing/Corporate Negotiate/Patnership Contract | E4: 12
A5: ST0004 | B5: Sales Region Sulawesi - Maluku Team | C5: Sulawesi, Maluku, North Maluku | D5: Corporate Negotiate/Patnership Contract | E5: 16
A6: ST0005 | B6: Sales Region Bali - Nusa Tenggara Team | C6: Bali, East & West Nusa Tenggara | D6: Corporate Negotiate/Patnership Contract | E6: 6

Sheet Invoice
A1: InvoiceID | B1: SalesOrderID | C1: ShipmentType | D1: WarehouseLocation | E1: TermsofPayment | F1: ShippingCost | G1: Taxes | H1: TotalDue
A2: IV0001 | B2: SO0001 | C2: Cargo | D2: Central Kalimantan | E2: COD | F2: 808800 | G2: 0.11 | H2: 1.2806106e+08
A3: IV0002 | B3: SO0002 | C3: Cargo | D3: South Kalimantan | E3: COD | F3: 808800 | G3: 0.11 | H3: 50615577
A4: IV0003 | B4: SO0003 | C4: Reguler | D4: Jakarta | E4: NET60 | F4: 8088 | G4: 0.11 | H4: 1.2230128e+09
A5: IV0004 | B5: SO0004 | C5: Cargo | D5: South Kalimantan | E5: COD | F5: 808800 | G5: 0.11 | H5: 12683633
A6: IV0005 | B6: SO0005 | C6: Reguler | D6: Jakarta | E6: NET60 | F6: 8088 | G6: 0.11 | H6: 278129688
A7: IV0006 | B7: SO0006 | C7: Cargo | D7: South Kalimantan | E7: COD | F7: 808800 | G7: 0.11 | H7: 13317878
A8: IV0007 | B8: SO0007 | C8: Reguler | D8: Jakarta | E8: NET90 | F8: 8088 | G8: 0.11 | H8: 4.7400892e+08
A9: IV0008 | B9: SO0008 | C9: Cargo | D9: West Nusa Tenggara | E9: NET90 | F9: 556050 | G9: 0.11 | H9: 6.8222585e+08
A10: IV0009 | B10: SO0009 | C10: Reguler | D10: East Java | E10: CBD | F10: 32352 | G10: 0.11 | H10: 1.9474839e+08
A11: IV0010 | B11: SO0010 | C11: Reguler | D11: East Java | E11: NET90 | F11: 32352 | G11: 0.11 | H11: 7.4271669e+08
A12: IV0011 | B12: SO0011 | C12: Cargo | D12: Central Kalimantan | E12: COD | F12: 808800 | G12: 0.11 | H12: 78721154
A13: IV0012 | B13: SO0012 | C13: Cargo | D13: North Maluku | E13: COD | F13: 859350 | G13: 0.11 | H13: 109139739
... A1029: IV1028 | B1029: SO1028 | C1029: Reguler | D1029: East Java | E1029: NET90 | F1029: 32352 | G1029: 0.11 | H1029: 533399229
